code/learn/three_step_make_a_cpu_by_verilog/code/def.v

// state of CPU
`define idle        1'b0
`define exec        1'b1

// Instructions
`define NOP         5'b0_0000
`define HALT        5'b0_0001
`define LOAD        5'b0_0010
`define STORE       5'b0_0011
`define SLL         5'b0_0100       // Shift Left Logic，高位填充0
`define SLA         5'b0_0101       // Shift Left Arithmetic，高位填充最高位的值
`define SRL         5'b0_0110
`define SRA         5'b0_0111
`define ADD         5'b0_1000
`define ADDI        5'b0_1001
`define SUB         5'b0_1010
`define SUBI        5'b0_1011
`define CMP         5'b0_1100
`define AND         5'b0_1101
`define OR          5'b0_1110
`define XOR         5'b0_1111
`define LDIH        5'b1_0000
`define ADDC        5'b1_0001
`define SUBC        5'b1_0010
`define SUIH        5'b1_0011
// 5'b1_0100
// 5'b1_0101
// 5'b1_0110
// 5'b1_0111
`define JUMP        5'b1_1000
`define JMPR        5'b1_1001
`define BZ          5'b1_1010
`define BNZ         5'b1_1011
`define BN          5'b1_1100
`define BNN         5'b1_1101
`define BC          5'b1_1110
`define BNC         5'b1_1111

// General Registers
`define gr0         3'b000
`define gr1         3'b001
`define gr2         3'b010
`define gr3         3'b011
`define gr4         3'b100
`define gr5         3'b101
`define gr6         3'b110
`define gr7         3'b111

code/learn/three_step_make_a_cpu_by_verilog/code/pcpu.v
// pipeline CPU
`timescale 1ns/1ns
`include "def.v"

module pcpu(
    input clk,                  // clock
    input ena,                  // enable CPU
    input rst_n,                // reset signal, Low is valid
    input start,                // start CPU
    input [15:0] i_datain,      // instruction data in
    input [15:0] d_datain,      // data data in
    output [7:0] i_addr,        // instruction address
    output [7:0] d_addr,        // data address
    output d_we,                // data write enable
    output [15:0] d_dataout     // data data output
);

    reg cf_buf;
    reg [15:0] ALUo;            // ALU output
    reg state, next_state;      // state of CPU
    reg zf,nf,cf,dw;            // Zero flag, Negative flag, Carry flag, Data Write Eanble flag
    reg [7:0] pc;
    reg [15:0] id_ir, ex_ir, mem_ir, wb_ir;     // Instructon Decode, Execute, Memeory, Write Back
    reg [15:0] reg_A, reg_B, reg_C, reg_C1, smdr, smdr1;    // smdr: data for save memroy directly
    reg [15:0] gr[7:0];         // general registers
    wire branch_flag;           // need branch jump? 

    /******************** CPU Control *******************/
    always @(posedge clk) begin
        if (!rst_n)
            state <= `idle;
        else
            state <= next_state;
    end

    always @(*) begin
        case (state)
            `idle:
                if (ena && start)
                    next_state <= `exec;
                else
                    next_state <= `idle;
            `exec:
                if (!ena || (wb_ir[15:11] == `HALT))
                    next_state <= `idle;
                else
                    next_state <= `exec;
            default:
                next_state <= `idle;
        endcase
    end

    /******************** IF: Instruction Fetch Stage *******************/
    assign i_addr = pc;
    
    always @(posedge clk or negedge rst_n) begin
        if (!rst_n) begin
            // Clear all output registers and wires at this stage when got reset signal
            id_ir <= {`NOP, 11'b000_0000_0000};
            pc <= 8'b0000_0000;
        end
        else if (state == `exec) begin
            id_ir <= i_datain;

            if (branch_flag)
                pc <= reg_C[7:0];
            else
                pc <= pc + 2;
        end
        else
            id_ir <= id_ir;
    end

    /******************** ID: Instruction Decode Stage *******************/
    always @(posedge clk or negedge rst_n) begin
        if (!rst_n) begin
            ex_ir <= {`NOP, 11'b000_0000_0000};
            reg_A <= 16'b0000_0000_0000_0000;
            reg_B <= 16'b0000_0000_0000_0000;
            smdr <= 16'b0000_0000_0000_0000;
        end
        else if (state == `exec) begin
            ex_ir <= id_ir;

            if (id_ir[15:11] == `STORE)
                smdr <= gr[id_ir[10:8]];
            else
                smdr <= smdr;
            
            if (id_ir[15:11] == `JUMP)
                reg_A <= 16'd0;
            else if (I_R1_TYPE(id_ir[15:11]))
                reg_A <= gr[id_ir[10:8]];
            else if (I_R2_TYPE(id_ir[15:11]))
                reg_A <= gr[id_ir[6:4]];
            else
                reg_A <= reg_A;
            
            if (I_V3_TYPE(id_ir[15:11]))
                reg_B <= {12'd0, id_ir[3:0]};
            else if (I_ZEROV2V3_TYPE(id_ir[15:11]))
                reg_B <= {8'd0, id_ir[7:0]};
            else if (I_V2V3ZERO_TYPE(id_ir[15:11]))
                reg_B <= {id_ir[7:0], 8'd0};
            else if (I_R3_TYPE(id_ir[15:11]))
                reg_B <= gr[id_ir[2:0]];
            else
                reg_B <= reg_B;
        end
    end

    /******************** EX: Execute Stage *******************/
    always @(posedge clk or negedge rst_n) begin
        if (!rst_n) begin
            mem_ir <= {`NOP, 11'b000_0000_0000};
            reg_C <= 16'b0000_0000_0000_0000;
            smdr1 <= 16'b0000_0000_0000_0000;
            dw <= 1'b0;
            zf <= 1'b0;
            nf <= 1'b0;
            cf <= 1'b0;
        end
        else if (state == `exec) begin
            reg_C <= ALUo;
            mem_ir <= ex_ir;

            // Handle zf/nf/cf flag
            if ((ex_ir[15:11] == `LDIH)
                || (ex_ir[15:11] == `SUIH)
                || (ex_ir[15:11] == `ADD)
                || (ex_ir[15:11] == `ADDI)
                || (ex_ir[15:11] == `ADDC)
                || (ex_ir[15:11] == `SUB)
                || (ex_ir[15:11] == `SUBI)
                || (ex_ir[15:11] == `SUBC)
                || (ex_ir[15:11] == `CMP)
                || (ex_ir[15:11] == `AND)
                || (ex_ir[15:11] == `OR)
                || (ex_ir[15:11] == `XOR)
                || (ex_ir[15:11] == `SLL)
                || (ex_ir[15:11] == `SRL)
                || (ex_ir[15:11] == `SLA)
                || (ex_ir[15:11] == `SRA)) begin
                cf <= cf_buf;
                if (ALUo == 16'd0)
                    zf <= 1'b1;
                else
                    zf <= 1'b0;

                if (ALUo[15] == 1'b1)
                    nf <= 1'b1;
                else
                    nf <= 1'b0;
            end
            else begin
                zf <= zf;
                nf <= nf;
                cf <= cf;
            end

            // Handle Data for store to memroy
            if (ex_ir[15:11] == `STORE) begin
                dw <= 1'b1;
                smdr1 <= smdr;
            end
            else begin
                dw <= 1'b0;
                smdr1 <= smdr1;
            end

        end
    end

    // execute instructions
    always @(*) begin
        if (ex_ir[15:11] == `AND) begin
            cf_buf <= 1'b0;
            ALUo <= reg_A & reg_B;
        end

        else if (ex_ir[15:11] == `OR) begin
            cf_buf <= 1'b0;
            ALUo <= reg_A | reg_B;
        end

        else if (ex_ir[15:11] == `XOR) begin
            cf_buf <= 1'b0;
            ALUo <= reg_A ^ reg_B;
        end

        else if (ex_ir[15:11] == `SLL)
            {cf_buf, ALUo[15:0]} <= {cf, reg_A[15:0]} << reg_B[3:0];
        else if (ex_ir[15:11] == `SRL)
            {ALUo[15:0], cf_buf} <= {reg_A[15:0], cf} >> reg_B[3:0];
        else if (ex_ir[15:11] == `SLA)
            {cf_buf, ALUo[15:0]} <= {cf, reg_A[15:0]} << reg_B[3:0];
        else if (ex_ir[15:11] == `SRA)
            {ALUo[15:0], cf_buf} <= {reg_A[15:0], cf} >> reg_B[3:0];
        else if ((ex_ir[15:11] == `SUB)
            || (ex_ir[15:11] == `SUBI)
            || (ex_ir[15:11] == `CMP)
            || (ex_ir[15:11] == `SUIH))
            {cf_buf, ALUo} <= reg_A - reg_B;
        else if (ex_ir[15:11] == `SUBC)
            {cf_buf, ALUo} <= reg_A - reg_B - cf;
        else if (ex_ir[15:11] == `ADDC)
            {cf_buf, ALUo} <= reg_A + reg_B + cf;
        else
            {cf_buf, ALUo} <= reg_A + reg_B;

    end


    /******************** MEM: Memory Operation *******************/
    assign d_addr = reg_C[7:0];
    assign d_we = dw;
    assign d_dataout = smdr1;
    assign branch_flag = ((mem_ir[15:11] == `JUMP)
        || (mem_ir[15:11] == `JMPR)
        || ((mem_ir[15:11] == `BZ) && (zf == 1'b1))
        || ((mem_ir[15:11] == `BNZ) && (zf == 1'b0))
        || ((mem_ir[15:11] == `BN) && (nf == 1'b1))
        || ((mem_ir[15:11] == `BNN) && (nf == 1'b0))
        || ((mem_ir[15:11] == `BC) && (cf == 1'b1))
        || ((mem_ir[15:11] == `BNC) && (cf == 1'b0)));

    always @(posedge clk or negedge rst_n) begin
        if (!rst_n) begin
            wb_ir <= {`NOP, 11'b000_0000_0000};
            reg_C1 <= 16'b0000_0000_0000_0000;
        end
        else if (state == `exec) begin
            wb_ir <= mem_ir;

            if (mem_ir[15:11] == `LOAD)
                reg_C1 <= d_datain;
            else
                reg_C1 <= reg_C;
        end
    end

    
    /******************** WB: Write Back *******************/

    always @(posedge clk or negedge rst_n) begin
        if (!rst_n) begin
            gr[0] <= 16'd0;
            gr[1] <= 16'd0;
            gr[2] <= 16'd0;
            gr[3] <= 16'd0;
            gr[4] <= 16'd0;
            gr[5] <= 16'd0;
            gr[6] <= 16'd0;
            gr[7] <= 16'd0;
        end
        else if (state == `exec) begin
            if (I_REG_TYPE(wb_ir[15:11]))
                gr[wb_ir[10:8]] <= reg_C1;
        end
    end

    
    /******************** Judge an instruction whether alter the value of a register *******************/
    function I_REG_TYPE;
        input [4:0] op;
        begin
            I_REG_TYPE = ((op == `LOAD)
                || (op == `LDIH)
                || (op == `ADD)
                || (op == `ADDI)
                || (op == `ADDC)
                || (op == `SUIH)
                || (op == `SUB)
                || (op == `SUBI)
                || (op == `SUBC)
                || (op == `AND)
                || (op == `OR)
                || (op == `XOR)
                || (op == `SLL)
                || (op == `SRL)
                || (op == `SLA)
                || (op == `SRA));
        end
    endfunction


    /******************** R1 as reg_A *******************/
    function I_R1_TYPE;
        input [4:0] op;
        begin
            I_R1_TYPE = ((op == `LDIH)
                || (op == `SUIH)
                || (op == `SUIH)
                || (op == `SUBI)
                || (op == `JMPR)
                || (op == `BZ)
                || (op == `BNZ)
                || (op == `BN)
                || (op == `BNN)
                || (op == `BC)
                || (op == `BNC));
        end
    endfunction

    /******************** R2 as reg_A *******************/
    function I_R2_TYPE;
        input [4:0] op;
        begin
            I_R2_TYPE = ((op == `LOAD)
                || (op == `STORE)
                || (op == `ADD)
                || (op == `ADDC)
                || (op == `SUB)
                || (op == `SUBC)
                || (op == `CMP)
                || (op == `AND)
                || (op == `OR)
                || (op == `XOR)
                || (op == `SLL)
                || (op == `SRL)
                || (op == `SLA)
                || (op == `SRA));
        end
    endfunction

    /******************** R3 as reg_B *******************/
    function I_R3_TYPE;
        input [4:0] op;
        begin
            I_R3_TYPE = ((op == `ADD)
                || (op == `ADDC)
                || (op == `SUB)
                || (op == `SUBC)
                || (op == `CMP)
                || (op == `AND)
                || (op == `OR)
                || (op == `XOR));
        end
    endfunction

    /******************** val3 as reg_A *******************/
    function I_V3_TYPE;
        input [4:0] op;
        begin
            I_V3_TYPE = ((op == `LOAD)
                || (op == `STORE)
                || (op == `SLL)
                || (op == `SRL)
                || (op == `SLA)
                || (op == `SRA));
        end
    endfunction

    /******************** {8'b0,val2,val3} as reg_B *******************/
    function I_ZEROV2V3_TYPE;
        input [4:0] op;
        begin
            I_ZEROV2V3_TYPE = ((op == `ADDI)
                    || (op == `SUBI)
                    || (op == `JUMP)
                    || (op == `JMPR)
                    || (op == `BZ)
                    || (op == `BNZ)
                    || (op == `BN)
                    || (op == `BNN)
                    || (op == `BC)
                    || (op == `BNC));
        end
    endfunction

    /******************** {val2,val3,8'b0} as reg_B *******************/
    function I_V2V3ZERO_TYPE;
        input [4:0] op;
        begin
            I_V2V3ZERO_TYPE = ((op == `LDIH)
                    || (op == `SUIH));
        end
    endfunction

endmodule

code/learn/three_step_make_a_cpu_by_verilog/code/tb_pcpu_state.v
// 测试 control unit 的 state 转移

`timescale 1ns/1ns
`include "pcpu.v"

module pcpu_tb();

    parameter DELAY = 20;

    reg clk, ena, rst_n, start;
    reg [15:0] i_datain, d_datain;
    wire [7:0] i_addr, d_addr;
    wire d_we;
    wire [15:0] d_dataout;

    pcpu u1(
        .clk            (clk        ),
        .ena            (ena        ),
        .rst_n          (rst_n      ),
        .start          (start      ),
        .i_datain       (i_datain   ),
        .d_datain       (d_datain   ),
        .i_addr         (i_addr     ),
        .d_addr         (d_addr     ),
        .d_we           (d_we       ),
        .d_dataout      (d_dataout  )
        );

    always #(DELAY/2) clk = ~clk;

    initial begin
        clk = 0; ena = 0; rst_n = 0; start = 0;
        i_datain = 0; d_datain = 0;
        
        #DELAY rst_n = 1;
        #DELAY ena = 1;
        #DELAY start = 1;
        #DELAY ena = 0;
        #DELAY ena = 1;
        #DELAY start = 0;
        
        #(DELAY*2) rst_n = 0;
        #(DELAY*2) rst_n = 1;

        #(DELAY*20) $finish;
    end

    // 打印信号
    initial 
        $monitor($time, ":rst=%b clk=%b ena=%d start=%d", rst_n,clk,ena,start);

    // 生成vcd波形文件
    initial begin
        $dumpfile("./build/tb_pcpu_state.vcd");
        $dumpvars(0, pcpu_tb);
        #10000 $finish;
    end
    
endmodule

code/learn/three_step_make_a_cpu_by_verilog/code/build/tb_pcpu_state.vcd
$date
	Sat Aug 14 10:39:24 2021
$end
$version
	Icarus Verilog
$end
$timescale
	1ns
$end
$scope module pcpu_tb $end
$var wire 8 ! i_addr [7:0] $end
$var wire 1 " d_we $end
$var wire 16 # d_dataout [15:0] $end
$var wire 8 $ d_addr [7:0] $end
$var reg 1 % clk $end
$var reg 16 & d_datain [15:0] $end
$var reg 1 ' ena $end
$var reg 16 ( i_datain [15:0] $end
$var reg 1 ) rst_n $end
$var reg 1 * start $end
$scope module u1 $end
$var wire 1 + branch_flag $end
$var wire 1 % clk $end
$var wire 16 , d_datain [15:0] $end
$var wire 16 - d_dataout [15:0] $end
$var wire 1 " d_we $end
$var wire 1 ' ena $end
$var wire 8 . i_addr [7:0] $end
$var wire 16 / i_datain [15:0] $end
$var wire 1 ) rst_n $end
$var wire 1 * start $end
$var wire 8 0 d_addr [7:0] $end
$var reg 16 1 ALUo [15:0] $end
$var reg 1 2 cf $end
$var reg 1 3 cf_buf $end
$var reg 1 4 dw $end
$var reg 16 5 ex_ir [15:0] $end
$var reg 16 6 id_ir [15:0] $end
$var reg 16 7 mem_ir [15:0] $end
$var reg 1 8 next_state $end
$var reg 1 9 nf $end
$var reg 8 : pc [7:0] $end
$var reg 16 ; reg_A [15:0] $end
$var reg 16 < reg_B [15:0] $end
$var reg 16 = reg_C [15:0] $end
$var reg 16 > reg_C1 [15:0] $end
$var reg 16 ? smdr [15:0] $end
$var reg 16 @ smdr1 [15:0] $end
$var reg 1 A state $end
$var reg 16 B wb_ir [15:0] $end
$var reg 1 C zf $end
$scope function I_R1_TYPE $end
$var reg 5 D op [4:0] $end
$upscope $end
$scope function I_R2_TYPE $end
$var reg 5 E op [4:0] $end
$upscope $end
$scope function I_R3_TYPE $end
$var reg 5 F op [4:0] $end
$upscope $end
$scope function I_REG_TYPE $end
$var reg 5 G op [4:0] $end
$upscope $end
$scope function I_V2V3ZERO_TYPE $end
$var reg 5 H op [4:0] $end
$upscope $end
$scope function I_V3_TYPE $end
$var reg 5 I op [4:0] $end
$upscope $end
$scope function I_ZEROV2V3_TYPE $end
$var reg 5 J op [4:0] $end
$upscope $end
$upscope $end
$upscope $end
$enddefinitions $end
#0
$dumpvars
bx J
bx I
bx H
bx G
bx F
bx E
bx D
0C
b0 B
xA
b0 @
b0 ?
b0 >
b0 =
b0 <
b0 ;
b0 :
09
08
b0 7
b0 6
b0 5
04
03
02
b0 1
b0 0
b0 /
b0 .
b0 -
b0 ,
0+
0*
0)
b0 (
0'
b0 &
0%
b0 $
b0 #
0"
b0 !
$end
#10
0A
1%
#20
0%
1)
#30
1%
#40
0%
1'
#50
1%
#60
18
0%
1*
#70
1A
1%
#80
08
0%
0'
#90
b10 !
b10 .
b10 :
0A
b0 G
b0 F
b0 H
b0 J
b0 I
b0 E
b0 D
1%
#100
18
0%
1'
#110
1A
1%
#120
0%
0*
#130
b100 !
b100 .
b100 :
1%
#140
0%
#150
b110 !
b110 .
b110 :
1%
#160
b0 !
b0 .
b0 :
0%
0)
#170
08
0A
1%
#180
0%
#190
1%
#200
0%
1)
