code/learn/verilog_examples/04_adder/full_adder/full_adder1.v
// 1 位全加器 - 门元件实现的
module full_adder1(a,b,cin,sum,cout);
input a,b,cin;
output sum,cout;
wire s1,m1,m2,m3;
and (m1,a,b),
    (m2,b,cin),
    (m3,a,cin);
xor (s1,a,b),
    (sum,s1,cin);
or  (cout,m1,m2,m3);
endmodule

code/learn/verilog_examples/04_adder/full_adder4/full_adder4_1.v
// 4 位级联全加器 - 结构描述的
`include "../full_adder/full_adder1.v"

module full_adder4_1(sum,cout,a,b,cin);
output [3:0] sum;
output cout;
input [3:0] a,b;
input cin;
wire cin1,cin2,cin3;

full_adder1 f0(a[0],b[0],cin,   sum[0],cin1);
full_adder1 f1(a[1],b[1],cin1,  sum[1],cin2);
full_adder1 f2(a[2],b[2],cin2,  sum[2],cin3);
full_adder1 f3(a[3],b[3],cin3,  sum[3],cout);

endmodule

code/learn/verilog_examples/04_adder/full_adder4/full_adder4_1_tb.v
`timescale 1ns/1ns
`include "full_adder4_1.v"

module full_adder4_1_tb;
reg [3:0] a,b;
reg cin;
wire [3:0] sum;
wire cout;
parameter DELAY = 20;

full_adder4_1 u1(sum,cout,a,b,cin);

always #(DELAY)     cin = ~cin;

always #(DELAY*2)   a = a + 1;

always #(DELAY*5)   b = b + 1;

initial begin
            a = 0; b = 0; cin = 0;
    #(DELAY*100)  $finish;
end

// 打印信号
initial 
    $monitor($time, ": (a,b,cin)=(%d,%d,%d), (cout,sum)=(%d,%d)",
        a,b,cin,cout,sum);

// 生成vcd波形文件
initial begin
    $dumpfile("./build/full_adder4_1_wave.vcd");
    $dumpvars(0, full_adder4_1_tb);
end

endmodule

code/learn/verilog_examples/04_adder/full_adder4/build/full_adder4_1_wave.vcd
$date
	Wed Aug 04 18:20:30 2021
$end
$version
	Icarus Verilog
$end
$timescale
	1ns
$end
$scope module full_adder4_1_tb $end
$var wire 4 ! sum [3:0] $end
$var wire 1 " cout $end
$var reg 4 # a [3:0] $end
$var reg 4 $ b [3:0] $end
$var reg 1 % cin $end
$scope module u1 $end
$var wire 4 & a [3:0] $end
$var wire 4 ' b [3:0] $end
$var wire 1 % cin $end
$var wire 4 ( sum [3:0] $end
$var wire 1 " cout $end
$var wire 1 ) cin3 $end
$var wire 1 * cin2 $end
$var wire 1 + cin1 $end
$scope module f0 $end
$var wire 1 , a $end
$var wire 1 - b $end
$var wire 1 % cin $end
$var wire 1 + cout $end
$var wire 1 . m1 $end
$var wire 1 / m2 $end
$var wire 1 0 m3 $end
$var wire 1 1 s1 $end
$var wire 1 2 sum $end
$upscope $end
$scope module f1 $end
$var wire 1 3 a $end
$var wire 1 4 b $end
$var wire 1 + cin $end
$var wire 1 * cout $end
$var wire 1 5 m1 $end
$var wire 1 6 m2 $end
$var wire 1 7 m3 $end
$var wire 1 8 s1 $end
$var wire 1 9 sum $end
$upscope $end
$scope module f2 $end
$var wire 1 : a $end
$var wire 1 ; b $end
$var wire 1 * cin $end
$var wire 1 ) cout $end
$var wire 1 < m1 $end
$var wire 1 = m2 $end
$var wire 1 > m3 $end
$var wire 1 ? s1 $end
$var wire 1 @ sum $end
$upscope $end
$scope module f3 $end
$var wire 1 A a $end
$var wire 1 B b $end
$var wire 1 ) cin $end
$var wire 1 " cout $end
$var wire 1 C m1 $end
$var wire 1 D m2 $end
$var wire 1 E m3 $end
$var wire 1 F s1 $end
$var wire 1 G sum $end
$upscope $end
$upscope $end
$upscope $end
$enddefinitions $end
#0
$dumpvars
0G
0F
0E
0D
0C
0B
0A
0@
0?
0>
0=
0<
0;
0:
09
08
07
06
05
04
03
02
01
00
0/
0.
0-
0,
0+
0*
0)
b0 (
b0 '
b0 &
0%
b0 $
b0 #
0"
b0 !
$end
#20
b1 !
b1 (
12
1%
#40
11
b1 !
b1 (
12
1,
0%
b1 #
b1 &
#60
19
1+
10
b10 !
b10 (
02
1%
#80
0@
0*
0+
01
07
18
00
b10 !
b10 (
02
0,
13
0%
b10 #
b10 &
#100
1@
1*
17
09
1+
11
1/
b100 !
b100 (
02
1-
1%
b1 $
b1 '
#120
1.
01
0/
b100 !
b100 (
02
1,
0%
b11 #
b11 &
#140
1/
10
b101 !
b101 (
12
1%
#160
0G
0*
0)
1@
0+
0.
11
07
08
0>
1?
0/
00
b101 !
b101 (
12
0,
03
1:
0%
b100 #
b100 &
#180
19
1+
1/
b110 !
b110 (
02
1%
#200
0G
0)
0>
1@
0*
0+
06
18
0/
b111 !
b111 (
12
1,
0-
14
0%
b101 #
b101 &
b10 $
b10 '
#220
1G
1)
1>
0@
1*
16
09
1+
10
b1000 !
b1000 (
02
1%
#240
06
0+
01
15
07
08
00
b1000 !
b1000 (
02
0,
13
0%
b110 #
b110 &
#260
b1001 !
b1001 (
12
1%
#280
11
b1001 !
b1001 (
12
1,
0%
b111 #
b111 &
#300
16
17
19
1+
1.
01
1/
10
b1011 !
b1011 (
12
1-
1%
b11 $
b11 '
#320
0*
06
0)
0@
0"
1G
0+
0.
11
05
07
18
0>
0?
0E
1F
0/
00
b1011 !
b1011 (
12
0,
03
0:
1A
0%
b1000 #
b1000 &
#340
1@
1*
16
09
1+
1/
b1100 !
b1100 (
02
1%
#360
1.
01
0/
b1100 !
b1100 (
02
1,
0%
b1001 #
b1001 &
#380
1/
10
b1101 !
b1101 (
12
1%
#400
0"
0*
0E
1G
19
0)
1@
0+
07
0.
06
0=
1?
0/
00
b1110 !
b1110 (
02
0,
13
0-
04
1;
0%
b1010 #
b1010 &
b100 $
b100 '
#420
b1111 !
b1111 (
12
1%
#440
11
b1111 !
b1111 (
12
1,
0%
b1011 #
b1011 &
#460
1"
1E
0G
1)
1=
0@
1*
17
09
1+
10
b0 !
b0 (
02
1%
#480
0=
0*
0@
0+
01
07
08
1<
0>
0?
00
b0 !
b0 (
02
0,
03
1:
0%
b1100 #
b1100 &
#500
19
1+
11
1/
b10 !
b10 (
02
1-
1%
b101 $
b101 '
#520
1.
01
0/
b10 !
b10 (
02
1,
0%
b1101 #
b1101 &
#540
1/
10
b11 !
b11 (
12
1%
#560
0=
0>
0@
0*
0+
0.
11
07
18
0/
00
b11 !
b11 (
12
0,
13
0%
b1110 #
b1110 &
#580
1=
1>
1@
1*
17
09
1+
1/
b100 !
b100 (
02
1%
#600
07
0+
15
06
08
0/
b101 !
b101 (
12
1,
0-
14
0%
b1111 #
b1111 &
b110 $
b110 '
#620
16
17
19
1+
10
b110 !
b110 (
02
1%
#640
0)
0=
0*
06
1@
0"
0G
0+
01
05
07
18
0<
0>
1?
0E
0F
00
b110 !
b110 (
02
0,
03
0:
0A
0%
b0 #
b0 &
#660
b111 !
b111 (
12
1%
#680
11
b111 !
b111 (
12
1,
0%
b1 #
b1 &
#700
1G
1)
1=
0@
1*
16
09
1+
1.
01
1/
10
b1001 !
b1001 (
12
1-
1%
b111 $
b111 '
#720
06
0+
0.
11
15
07
08
0/
00
b1001 !
b1001 (
12
0,
13
0%
b10 #
b10 &
#740
16
17
19
1+
1/
b1010 !
b1010 (
02
1%
#760
1.
01
0/
b1010 !
b1010 (
02
1,
0%
b11 #
b11 &
#780
1/
10
b1011 !
b1011 (
12
1%
#800
0)
1@
09
0*
0"
1G
0+
07
0>
0.
05
06
0=
0D
1F
0/
00
b1100 !
b1100 (
02
0,
03
1:
0-
04
0;
1B
0%
b100 #
b100 &
b1000 $
b1000 '
#820
b1101 !
b1101 (
12
1%
#840
11
b1101 !
b1101 (
12
1,
0%
b101 #
b101 &
#860
19
1+
10
b1110 !
b1110 (
02
1%
#880
0"
0D
1G
0)
0>
1@
0*
0+
01
07
18
00
b1110 !
b1110 (
02
0,
13
0%
b110 #
b110 &
#900
1"
1D
0G
1)
1>
0@
1*
17
09
1+
11
1/
b0 !
b0 (
02
1-
1%
b1001 $
b1001 '
#920
1.
01
0/
b0 !
b0 (
02
1,
0%
b111 #
b111 &
#940
1/
10
b1 !
b1 (
12
1%
#960
0D
0*
0)
0@
0G
0+
0.
11
07
08
0>
0?
1C
0E
0F
0/
00
b1 !
b1 (
12
0,
03
0:
1A
0%
b1000 #
b1000 &
#980
19
1+
1/
b10 !
b10 (
02
1%
#1000
0@
0*
0+
06
18
0/
b11 !
b11 (
12
1,
0-
14
0%
b1001 #
b1001 &
b1010 $
b1010 '
#1020
1@
1*
16
09
1+
10
b100 !
b100 (
02
1%
#1040
06
0+
01
15
07
08
00
b100 !
b100 (
02
0,
13
0%
b1010 #
b1010 &
#1060
b101 !
b101 (
12
1%
#1080
11
b101 !
b101 (
12
1,
0%
b1011 #
b1011 &
#1100
16
17
19
1+
1.
01
1/
10
b111 !
b111 (
12
1-
1%
b1011 $
b1011 '
#1120
0*
0D
0E
0G
06
0)
1@
0+
0.
11
05
07
18
0>
1?
0/
00
b111 !
b111 (
12
0,
03
1:
0%
b1100 #
b1100 &
#1140
1D
1E
1G
1)
1>
0@
1*
16
09
1+
1/
b1000 !
b1000 (
02
1%
#1160
1.
01
0/
b1000 !
b1000 (
02
1,
0%
b1101 #
b1101 &
#1180
1/
10
b1001 !
b1001 (
12
1%
#1200
0>
0*
19
0@
0+
07
0.
06
1<
0=
0?
0/
00
b1010 !
b1010 (
02
0,
13
0-
04
1;
0%
b1110 #
b1110 &
b1100 $
b1100 '
#1220
b1011 !
b1011 (
12
1%
#1240
11
b1011 !
b1011 (
12
1,
0%
b1111 #
b1111 &
#1260
1=
1>
1@
1*
17
09
1+
10
b1100 !
b1100 (
02
1%
#1280
0"
0D
0)
0=
0*
1@
1G
0+
01
07
08
0<
0>
1?
0C
0E
1F
00
b1100 !
b1100 (
02
0,
03
0:
0A
0%
b0 #
b0 &
#1300
19
1+
11
1/
b1110 !
b1110 (
02
1-
1%
b1101 $
b1101 '
#1320
1.
01
0/
b1110 !
b1110 (
02
1,
0%
b1 #
b1 &
#1340
1/
10
b1111 !
b1111 (
12
1%
#1360
0"
0D
1G
0)
0=
1@
0*
0+
0.
11
07
18
0/
00
b1111 !
b1111 (
12
0,
13
0%
b10 #
b10 &
#1380
1"
1D
0G
1)
1=
0@
1*
17
09
1+
1/
b0 !
b0 (
02
1%
#1400
07
0+
15
06
08
0/
b1 !
b1 (
12
1,
0-
14
0%
b11 #
b11 &
b1110 $
b1110 '
#1420
16
17
19
1+
10
b10 !
b10 (
02
1%
#1440
0=
0*
06
0@
0+
01
05
07
18
1<
0>
0?
00
b10 !
b10 (
02
0,
03
1:
0%
b100 #
b100 &
#1460
b11 !
b11 (
12
1%
#1480
11
b11 !
b11 (
12
1,
0%
b101 #
b101 &
#1500
1=
1>
1@
1*
16
09
1+
1.
01
1/
10
b101 !
b101 (
12
1-
1%
b1111 $
b1111 '
#1520
06
0+
0.
11
15
07
08
0/
00
b101 !
b101 (
12
0,
13
0%
b110 #
b110 &
#1540
16
17
19
1+
1/
b110 !
b110 (
02
1%
#1560
1.
01
0/
b110 !
b110 (
02
1,
0%
b111 #
b111 &
#1580
1/
10
b111 !
b111 (
12
1%
#1600
0"
0@
1G
09
0*
0)
0+
07
0>
0E
0.
05
06
0<
0=
0D
0/
00
b1000 !
b1000 (
02
0,
03
0:
1A
0-
04
0;
0B
0%
b1000 #
b1000 &
b0 $
b0 '
#1620
b1001 !
b1001 (
12
1%
#1640
11
b1001 !
b1001 (
12
1,
0%
b1001 #
b1001 &
#1660
19
1+
10
b1010 !
b1010 (
02
1%
#1680
0@
0*
0+
01
07
18
00
b1010 !
b1010 (
02
0,
13
0%
b1010 #
b1010 &
#1700
1@
1*
17
09
1+
11
1/
b1100 !
b1100 (
02
1-
1%
b1 $
b1 '
#1720
1.
01
0/
b1100 !
b1100 (
02
1,
0%
b1011 #
b1011 &
#1740
1/
10
b1101 !
b1101 (
12
1%
#1760
0"
0E
1G
0*
0)
1@
0+
0.
11
07
08
0>
1?
0/
00
b1101 !
b1101 (
12
0,
03
1:
0%
b1100 #
b1100 &
#1780
19
1+
1/
b1110 !
b1110 (
02
1%
#1800
0"
0E
1G
0)
0>
1@
0*
0+
06
18
0/
b1111 !
b1111 (
12
1,
0-
14
0%
b1101 #
b1101 &
b10 $
b10 '
#1820
1"
1E
0G
1)
1>
0@
1*
16
09
1+
10
b0 !
b0 (
02
1%
#1840
06
0+
01
15
07
08
00
b0 !
b0 (
02
0,
13
0%
b1110 #
b1110 &
#1860
b1 !
b1 (
12
1%
#1880
11
b1 !
b1 (
12
1,
0%
b1111 #
b1111 &
#1900
16
17
19
1+
1.
01
1/
10
b11 !
b11 (
12
1-
1%
b11 $
b11 '
#1920
0*
06
0)
0@
0"
0G
0+
0.
11
05
07
18
0>
0?
0E
0F
0/
00
b11 !
b11 (
12
0,
03
0:
0A
0%
b0 #
b0 &
#1940
1@
1*
16
09
1+
1/
b100 !
b100 (
02
1%
#1960
1.
01
0/
b100 !
b100 (
02
1,
0%
b1 #
b1 &
#1980
1/
10
b101 !
b101 (
12
1%
#2000
0*
0G
19
0)
1@
0+
07
0.
06
0=
1?
0/
00
b110 !
b110 (
02
0,
13
0-
04
1;
0%
b10 #
b10 &
b100 $
b100 '
