code/learn/verilog_examples/04_adder/full_adder4/full_adder4_2.v
// 4 位级联全加器 - 数据流描述的
module full_adder4_2(sum,cout,a,b,cin);
output [3:0] sum;
output cout;
input [3:0] a,b;
input cin;

assign {cout,sum} = a + b + cin;

endmodule

code/learn/verilog_examples/04_adder/full_adder4/full_adder4_2_tb.v
`timescale 1ns/1ns
`include "full_adder4_2.v"

module full_adder4_2_tb;
reg [3:0] a,b;
reg cin;
wire [3:0] sum;
wire cout;
integer i,j;
parameter DELAY = 20;

full_adder4_2 u1(sum,cout,a,b,cin);

always #(DELAY)     cin = ~cin;

initial begin
    a = 0; b = 0; cin = 0;
    for (i = 1; i < 16; i = i + 1)
        #DELAY a = i;
end

initial begin
    for (j = 1; j < 16; j = j + 1)
        #(DELAY*2) b = j;
end

// 打印信号
initial begin 
    $monitor($time, ": %d + %d + %b = {%b,%d}",
        a,b,cin,cout,sum);
    
    #(DELAY*100) $finish;
end

// 生成vcd波形文件
initial begin
    $dumpfile("./build/full_adder4_2_wave.vcd");
    $dumpvars(0, full_adder4_2_tb);
end

endmodule

code/learn/verilog_examples/04_adder/full_adder4/build/full_adder4_2_wave.vcd
$date
	Wed Aug 04 18:44:39 2021
$end
$version
	Icarus Verilog
$end
$timescale
	1ns
$end
$scope module full_adder4_2_tb $end
$var wire 4 ! sum [3:0] $end
$var wire 1 " cout $end
$var reg 4 # a [3:0] $end
$var reg 4 $ b [3:0] $end
$var reg 1 % cin $end
$var integer 32 & i [31:0] $end
$var integer 32 ' j [31:0] $end
$scope module u1 $end
$var wire 4 ( a [3:0] $end
$var wire 4 ) b [3:0] $end
$var wire 1 % cin $end
$var wire 4 * sum [3:0] $end
$var wire 1 " cout $end
$upscope $end
$upscope $end
$enddefinitions $end
#0
$dumpvars
b0 *
b0 )
b0 (
b1 '
b1 &
0%
b0 $
b0 #
0"
b0 !
$end
#20
b10 !
b10 *
b10 &
b1 #
b1 (
1%
#40
b11 !
b11 *
b11 &
b10 #
b10 (
0%
b10 '
b1 $
b1 )
#60
b101 !
b101 *
b100 &
b11 #
b11 (
1%
#80
b110 !
b110 *
b101 &
b100 #
b100 (
0%
b11 '
b10 $
b10 )
#100
b1000 !
b1000 *
b110 &
b101 #
b101 (
1%
#120
b1001 !
b1001 *
b111 &
b110 #
b110 (
0%
b100 '
b11 $
b11 )
#140
b1011 !
b1011 *
b1000 &
b111 #
b111 (
1%
#160
b1100 !
b1100 *
b1001 &
b1000 #
b1000 (
0%
b101 '
b100 $
b100 )
#180
b1110 !
b1110 *
b1010 &
b1001 #
b1001 (
1%
#200
b1111 !
b1111 *
b1011 &
b1010 #
b1010 (
0%
b110 '
b101 $
b101 )
#220
b1 !
b1 *
1"
b1100 &
b1011 #
b1011 (
1%
#240
b10 !
b10 *
b1101 &
b1100 #
b1100 (
0%
b111 '
b110 $
b110 )
#260
b100 !
b100 *
b1110 &
b1101 #
b1101 (
1%
#280
b101 !
b101 *
b1111 &
b1110 #
b1110 (
0%
b1000 '
b111 $
b111 )
#300
b111 !
b111 *
b10000 &
b1111 #
b1111 (
1%
#320
0%
b1001 '
b1000 $
b1000 )
#340
b1000 !
b1000 *
1%
#360
0%
b1010 '
b1001 $
b1001 )
#380
b1001 !
b1001 *
1%
#400
0%
b1011 '
b1010 $
b1010 )
#420
b1010 !
b1010 *
1%
#440
0%
b1100 '
b1011 $
b1011 )
#460
b1011 !
b1011 *
1%
#480
0%
b1101 '
b1100 $
b1100 )
#500
b1100 !
b1100 *
1%
#520
0%
b1110 '
b1101 $
b1101 )
#540
b1101 !
b1101 *
1%
#560
0%
b1111 '
b1110 $
b1110 )
#580
b1110 !
b1110 *
1%
#600
0%
b10000 '
b1111 $
b1111 )
#620
b1111 !
b1111 *
1%
#640
b1110 !
b1110 *
0%
#660
b1111 !
b1111 *
1%
#680
b1110 !
b1110 *
0%
#700
b1111 !
b1111 *
1%
#720
b1110 !
b1110 *
0%
#740
b1111 !
b1111 *
1%
#760
b1110 !
b1110 *
0%
#780
b1111 !
b1111 *
1%
#800
b1110 !
b1110 *
0%
#820
b1111 !
b1111 *
1%
#840
b1110 !
b1110 *
0%
#860
b1111 !
b1111 *
1%
#880
b1110 !
b1110 *
0%
#900
b1111 !
b1111 *
1%
#920
b1110 !
b1110 *
0%
#940
b1111 !
b1111 *
1%
#960
b1110 !
b1110 *
0%
#980
b1111 !
b1111 *
1%
#1000
b1110 !
b1110 *
0%
#1020
b1111 !
b1111 *
1%
#1040
b1110 !
b1110 *
0%
#1060
b1111 !
b1111 *
1%
#1080
b1110 !
b1110 *
0%
#1100
b1111 !
b1111 *
1%
#1120
b1110 !
b1110 *
0%
#1140
b1111 !
b1111 *
1%
#1160
b1110 !
b1110 *
0%
#1180
b1111 !
b1111 *
1%
#1200
b1110 !
b1110 *
0%
#1220
b1111 !
b1111 *
1%
#1240
b1110 !
b1110 *
0%
#1260
b1111 !
b1111 *
1%
#1280
b1110 !
b1110 *
0%
#1300
b1111 !
b1111 *
1%
#1320
b1110 !
b1110 *
0%
#1340
b1111 !
b1111 *
1%
#1360
b1110 !
b1110 *
0%
#1380
b1111 !
b1111 *
1%
#1400
b1110 !
b1110 *
0%
#1420
b1111 !
b1111 *
1%
#1440
b1110 !
b1110 *
0%
#1460
b1111 !
b1111 *
1%
#1480
b1110 !
b1110 *
0%
#1500
b1111 !
b1111 *
1%
#1520
b1110 !
b1110 *
0%
#1540
b1111 !
b1111 *
1%
#1560
b1110 !
b1110 *
0%
#1580
b1111 !
b1111 *
1%
#1600
b1110 !
b1110 *
0%
#1620
b1111 !
b1111 *
1%
#1640
b1110 !
b1110 *
0%
#1660
b1111 !
b1111 *
1%
#1680
b1110 !
b1110 *
0%
#1700
b1111 !
b1111 *
1%
#1720
b1110 !
b1110 *
0%
#1740
b1111 !
b1111 *
1%
#1760
b1110 !
b1110 *
0%
#1780
b1111 !
b1111 *
1%
#1800
b1110 !
b1110 *
0%
#1820
b1111 !
b1111 *
1%
#1840
b1110 !
b1110 *
0%
#1860
b1111 !
b1111 *
1%
#1880
b1110 !
b1110 *
0%
#1900
b1111 !
b1111 *
1%
#1920
b1110 !
b1110 *
0%
#1940
b1111 !
b1111 *
1%
#1960
b1110 !
b1110 *
0%
#1980
b1111 !
b1111 *
1%
#2000
b1110 !
b1110 *
0%
