code/oscpu-my/cpu/defines.v

`timescale 1ns / 1ps

`define ZERO_WORD  64'h00000000_00000000
`define REG_BUS    63 : 0
`define INST_ADDI  8'h11

code/oscpu-my/cpu/rom.v
/*
    ROM模块

    功能：
    1. 支持读
    2. 支持调试模式，允许对ROM进行初始化，设置初始化完成标志
*/

`include "defines.v"

module rom(
    input   wire                        rst,
    input   wire                        clk,

    input   wire    [`ROM_ADDR_BUS]     raddr_i,        // 要读取的地址
    output  reg     [`ROM_DATA_BUS]     rdata_o,        // 读取到的数据

    // (调试用，开机先写入ROM，并设置初始化完毕标志)
    input   wire                        we_i,           // 写入请求
    input   wire    [`ROM_ADDR_BUS]     waddr_i,        // 要写入的地址
    input   reg     [`ROM_DATA_BUS]     wdata_i,        // 读写入的数据
    input   wire                        inited_i,       // ROM是否已初始化完毕（外部设置）
    output  wire                        inited_o        // ROM是否已初始化完毕（内部反馈）
);

    reg [`ROM_DATA_BUS] mem [`ROM_SIZE_BUS];
    
    // 读取
    assign rdata_o = (!rst) ? mem[raddr_i] : `ROM_DATA_ZERO;

    // 写入
    always @(posedge clk or posedge rst)
    begin
        if (!rst && we_i) begin
            mem[waddr_i] <= wdata_i;
        end
    end

    // 初始化完毕
    always @(posedge clk or posedge rst)
    begin
        if (rst) begin
            inited_o <= 0;
        end
        else begin
            inited_o <= inited_i;
        end
    end
    
endmodule

code/oscpu-my/cpu/build/ram-test.vcd
$version Generated by VerilatedVcd $end
$date Sun Aug 15 17:45:35 2021 $end
$timescale 1ps $end

 $scope module TOP $end
  $var wire  1 $ clk $end
  $var wire  1 * inited_i $end
  $var wire  1 + inited_o $end
  $var wire 12 % raddr_i [11:0] $end
  $var wire 32 & rdata_o [31:0] $end
  $var wire  1 # rst $end
  $var wire 12 ( waddr_i [11:0] $end
  $var wire 32 ) wdata_i [31:0] $end
  $var wire  1 ' we_i $end
  $scope module rom $end
   $var wire  1 $ clk $end
   $var wire  1 * inited_i $end
   $var wire  1 + inited_o $end
   $var wire 12 % raddr_i [11:0] $end
   $var wire 32 & rdata_o [31:0] $end
   $var wire  1 # rst $end
   $var wire 12 ( waddr_i [11:0] $end
   $var wire 32 ) wdata_i [31:0] $end
   $var wire  1 ' we_i $end
  $upscope $end
 $upscope $end
$enddefinitions $end


#0
1#
0$
b000000000000 %
b00000000000000000000000000000000 &
0'
b000000000000 (
b00000000000000000000000000000000 )
0*
0+
#1
#2
#3
#4
#5
1$
#6
#7
#8
#9
#10
0#
0$
#11
b00000000000000000000000000010000 )
#12
1'
#13
#14
#15
1$
b00000000000000000000000000010000 &
#16
#17
#18
0'
#19
#20
0$
#21
b000000000001 (
b00000000000000000000000000010001 )
#22
1'
#23
#24
#25
1$
#26
#27
#28
0'
#29
#30
0$
#31
b000000000010 (
b00000000000000000000000000010010 )
#32
1'
#33
#34
#35
1$
#36
#37
#38
0'
#39
#40
0$
#41
b000000000011 (
b00000000000000000000000000010011 )
#42
1'
#43
#44
#45
1$
#46
#47
#48
0'
#49
#50
0$
#51
b000000000100 (
b00000000000000000000000000010100 )
#52
1'
#53
#54
#55
1$
#56
#57
#58
0'
#59
#60
0$
#61
b000000000101 (
b00000000000000000000000000010101 )
#62
1'
#63
#64
#65
1$
#66
#67
#68
0'
#69
#70
0$
#71
b000000000110 (
b00000000000000000000000000010110 )
#72
1'
#73
#74
#75
1$
#76
#77
#78
0'
#79
#80
0$
#81
b000000000111 (
b00000000000000000000000000010111 )
#82
1'
#83
#84
#85
1$
#86
#87
#88
0'
#89
#90
0$
#91
b000000001000 (
b00000000000000000000000000011000 )
#92
1'
#93
#94
#95
1$
#96
#97
#98
0'
#99
#100
0$
#101
#102
#103
#104
#105
1$
#106
#107
#108
#109
#110
0$
#111
b000000000001 %
b00000000000000000000000000010001 &
#112
#113
#114
#115
1$
#116
#117
#118
#119
#120
0$
#121
b000000000010 %
b00000000000000000000000000010010 &
#122
#123
#124
#125
1$
#126
#127
#128
#129
#130
0$
#131
b000000000011 %
b00000000000000000000000000010011 &
#132
#133
#134
#135
1$
#136
#137
#138
#139
#140
0$
#141
b000000000100 %
b00000000000000000000000000010100 &
#142
#143
#144
#145
1$
#146
#147
#148
#149
#150
0$
#151
b000000000101 %
b00000000000000000000000000010101 &
#152
#153
#154
#155
1$
#156
#157
#158
#159
#160
0$
#161
b000000000110 %
b00000000000000000000000000010110 &
#162
#163
#164
#165
1$
#166
#167
#168
#169
#170
0$
#171
b000000000111 %
b00000000000000000000000000010111 &
#172
#173
#174
#175
1$
#176
#177
#178
#179
#180
0$
#181
b000000001000 %
b00000000000000000000000000011000 &
#182
#183
#184
#185
1$
#186
#187
#188
#189
#190
0$
#191
b000000001001 %
b00000000000000000000000000000000 &
#192
#193
#194
#195
1$
#196
#197
#198
#199
#200
0$
#201
b000000001010 %
#202
#203
#204
#205
1$
#206
#207
#208
#209
#210
0$
#211
b000000001011 %
#212
#213
#214
#215
1$
#216
#217
#218
#219
#220
0$
#221
b000000001100 %
#222
#223
#224
#225
1$
#226
#227
#228
#229
#230
0$
#231
b000000001101 %
#232
#233
#234
#235
1$
#236
#237
#238
#239
#240
0$
#241
b000000001110 %
#242
#243
#244
#245
1$
#246
#247
#248
#249
#250
0$
#251
b000000001111 %
#252
#253
#254
#255
1$
#256
#257
#258
#259
#260
0$
#261
b000000010000 %
#262
#263
#264
#265
1$
#266
#267
#268
#269
#270
0$
#271
b000000010001 %
#272
#273
#274
#275
1$
#276
#277
#278
#279
#280
0$
#281
b000000010010 %
#282
#283
#284
#285
1$
#286
#287
#288
#289
#290
0$
#291
b000000010011 %
#292
#293
#294
#295
1$
#296
#297
#298
#299
#300
0$
#301
b000001100100 %
b000001100100 (
b01010101011001100111011100000000 )
#302
1'
#303
#304
#305
1$
b01010101011001100111011100000000 &
#306
#307
#308
#309
#310
0$
#311
b000001100101 %
b00000000000000000000000000000000 &
b000001100101 (
b01010101011001100111011100000010 )
#312
#313
#314
#315
1$
b01010101011001100111011100000010 &
#316
#317
#318
#319
#320
0$
#321
b000001100110 %
b00000000000000000000000000000000 &
b000001100110 (
b01010101011001100111011100000100 )
#322
#323
#324
#325
1$
b01010101011001100111011100000100 &
#326
#327
#328
#329
#330
0$
#331
b000001100111 %
b00000000000000000000000000000000 &
b000001100111 (
b01010101011001100111011100000110 )
#332
#333
#334
#335
1$
b01010101011001100111011100000110 &
#336
#337
#338
#339
#340
0$
#341
b000001101000 %
b00000000000000000000000000000000 &
b000001101000 (
b01010101011001100111011100001000 )
#342
#343
#344
#345
1$
b01010101011001100111011100001000 &
#346
#347
#348
#349
#350
0$
#351
b000001101001 %
b00000000000000000000000000000000 &
b000001101001 (
b01010101011001100111011100001010 )
#352
#353
#354
#355
1$
b01010101011001100111011100001010 &
#356
#357
#358
#359
#360
0$
#361
b000001101010 %
b00000000000000000000000000000000 &
b000001101010 (
b01010101011001100111011100001100 )
#362
#363
#364
#365
1$
b01010101011001100111011100001100 &
#366
#367
#368
#369
#370
0$
#371
b000001101011 %
b00000000000000000000000000000000 &
b000001101011 (
b01010101011001100111011100001110 )
#372
#373
#374
#375
1$
b01010101011001100111011100001110 &
#376
#377
#378
#379
#380
0$
#381
b000001101100 %
b00000000000000000000000000000000 &
b000001101100 (
b01010101011001100111011100010000 )
#382
#383
#384
#385
1$
b01010101011001100111011100010000 &
#386
#387
#388
#389
#390
0$
#391
b000001101101 %
b00000000000000000000000000000000 &
b000001101101 (
b01010101011001100111011100010010 )
#392
#393
#394
#395
1$
b01010101011001100111011100010010 &
#396
#397
#398
#399
#400
0$
#401
b000001101110 %
b00000000000000000000000000000000 &
b000001101110 (
b01010101011001100111011100010100 )
#402
#403
#404
#405
1$
b01010101011001100111011100010100 &
#406
#407
#408
#409
#410
0$
#411
b000001101111 %
b00000000000000000000000000000000 &
b000001101111 (
b01010101011001100111011100010110 )
#412
#413
#414
#415
1$
b01010101011001100111011100010110 &
#416
#417
#418
#419
#420
0$
#421
b000001110000 %
b00000000000000000000000000000000 &
b000001110000 (
b01010101011001100111011100011000 )
#422
#423
#424
#425
1$
b01010101011001100111011100011000 &
#426
#427
#428
#429
#430
0$
#431
b000001110001 %
b00000000000000000000000000000000 &
b000001110001 (
b01010101011001100111011100011010 )
#432
#433
#434
#435
1$
b01010101011001100111011100011010 &
#436
#437
#438
#439
#440
0$
#441
b000001110010 %
b00000000000000000000000000000000 &
b000001110010 (
b01010101011001100111011100011100 )
#442
#443
#444
#445
1$
b01010101011001100111011100011100 &
#446
#447
#448
#449
#450
0$
#451
b000001110011 %
b00000000000000000000000000000000 &
b000001110011 (
b01010101011001100111011100011110 )
#452
#453
#454
#455
1$
b01010101011001100111011100011110 &
#456
#457
#458
#459
#460
0$
#461
b000001110100 %
b00000000000000000000000000000000 &
b000001110100 (
b01010101011001100111011100100000 )
#462
#463
#464
#465
1$
b01010101011001100111011100100000 &
#466
#467
#468
#469
#470
0$
#471
b000001110101 %
b00000000000000000000000000000000 &
b000001110101 (
b01010101011001100111011100100010 )
#472
#473
#474
#475
1$
b01010101011001100111011100100010 &
#476
#477
#478
#479
#480
0$
#481
b000001110110 %
b00000000000000000000000000000000 &
b000001110110 (
b01010101011001100111011100100100 )
#482
#483
#484
#485
1$
b01010101011001100111011100100100 &
#486
#487
#488
#489
#490
0$
#491
b000001110111 %
b00000000000000000000000000000000 &
b000001110111 (
b01010101011001100111011100100110 )
#492
#493
#494
#495
1$
b01010101011001100111011100100110 &
#496
#497
#498
#499
#500
0$
#501
b000001111000 %
b00000000000000000000000000000000 &
b000001111000 (
b01010101011001100111011100101000 )
#502
#503
#504
#505
1$
b01010101011001100111011100101000 &
#506
#507
#508
#509
#510
0$
#511
b000001111001 %
b00000000000000000000000000000000 &
b000001111001 (
b01010101011001100111011100101010 )
#512
#513
#514
#515
1$
b01010101011001100111011100101010 &
#516
#517
#518
#519
#520
0$
#521
b000001111010 %
b00000000000000000000000000000000 &
b000001111010 (
b01010101011001100111011100101100 )
#522
#523
#524
#525
1$
b01010101011001100111011100101100 &
#526
#527
#528
#529
#530
0$
#531
b000001111011 %
b00000000000000000000000000000000 &
b000001111011 (
b01010101011001100111011100101110 )
#532
#533
#534
#535
1$
b01010101011001100111011100101110 &
#536
#537
#538
#539
#540
0$
#541
b000001111100 %
b00000000000000000000000000000000 &
b000001111100 (
b01010101011001100111011100110000 )
#542
#543
#544
#545
1$
b01010101011001100111011100110000 &
#546
#547
#548
#549
#550
0$
#551
b000001111101 %
b00000000000000000000000000000000 &
b000001111101 (
b01010101011001100111011100110010 )
#552
#553
#554
#555
1$
b01010101011001100111011100110010 &
#556
#557
#558
#559
#560
0$
#561
b000001111110 %
b00000000000000000000000000000000 &
b000001111110 (
b01010101011001100111011100110100 )
#562
#563
#564
#565
1$
b01010101011001100111011100110100 &
#566
#567
#568
#569
#570
0$
#571
b000001111111 %
b00000000000000000000000000000000 &
b000001111111 (
b01010101011001100111011100110110 )
#572
#573
#574
#575
1$
b01010101011001100111011100110110 &
#576
#577
#578
#579
#580
0$
#581
b000010000000 %
b00000000000000000000000000000000 &
b000010000000 (
b01010101011001100111011100111000 )
#582
#583
#584
#585
1$
b01010101011001100111011100111000 &
#586
#587
#588
#589
#590
0$
#591
b000010000001 %
b00000000000000000000000000000000 &
b000010000001 (
b01010101011001100111011100111010 )
#592
#593
#594
#595
1$
b01010101011001100111011100111010 &
#596
#597
#598
#599
#600
0$
#601
b000010000010 %
b00000000000000000000000000000000 &
b000010000010 (
b01010101011001100111011100111100 )
#602
#603
#604
#605
1$
b01010101011001100111011100111100 &
#606
#607
#608
#609
#610
0$
#611
b000010000011 %
b00000000000000000000000000000000 &
b000010000011 (
b01010101011001100111011100111110 )
#612
#613
#614
#615
1$
b01010101011001100111011100111110 &
#616
#617
#618
#619
#620
0$
#621
b000010000100 %
b00000000000000000000000000000000 &
b000010000100 (
b01010101011001100111011101000000 )
#622
#623
#624
#625
1$
b01010101011001100111011101000000 &
#626
#627
#628
#629
#630
0$
#631
b000010000101 %
b00000000000000000000000000000000 &
b000010000101 (
b01010101011001100111011101000010 )
#632
#633
#634
#635
1$
b01010101011001100111011101000010 &
#636
#637
#638
#639
#640
0$
#641
b000010000110 %
b00000000000000000000000000000000 &
b000010000110 (
b01010101011001100111011101000100 )
#642
#643
#644
#645
1$
b01010101011001100111011101000100 &
#646
#647
#648
#649
#650
0$
#651
b000010000111 %
b00000000000000000000000000000000 &
b000010000111 (
b01010101011001100111011101000110 )
#652
#653
#654
#655
1$
b01010101011001100111011101000110 &
#656
#657
#658
#659
#660
0$
#661
b000010001000 %
b00000000000000000000000000000000 &
b000010001000 (
b01010101011001100111011101001000 )
#662
#663
#664
#665
1$
b01010101011001100111011101001000 &
#666
#667
#668
#669
#670
0$
#671
b000010001001 %
b00000000000000000000000000000000 &
b000010001001 (
b01010101011001100111011101001010 )
#672
#673
#674
#675
1$
b01010101011001100111011101001010 &
#676
#677
#678
#679
#680
0$
#681
b000010001010 %
b00000000000000000000000000000000 &
b000010001010 (
b01010101011001100111011101001100 )
#682
#683
#684
#685
1$
b01010101011001100111011101001100 &
#686
#687
#688
#689
#690
0$
#691
b000010001011 %
b00000000000000000000000000000000 &
b000010001011 (
b01010101011001100111011101001110 )
#692
#693
#694
#695
1$
b01010101011001100111011101001110 &
#696
#697
#698
#699
#700
0$
#701
b000010001100 %
b00000000000000000000000000000000 &
b000010001100 (
b01010101011001100111011101010000 )
#702
#703
#704
#705
1$
b01010101011001100111011101010000 &
#706
#707
#708
#709
#710
0$
#711
b000010001101 %
b00000000000000000000000000000000 &
b000010001101 (
b01010101011001100111011101010010 )
#712
#713
#714
#715
1$
b01010101011001100111011101010010 &
#716
#717
#718
#719
#720
0$
#721
b000010001110 %
b00000000000000000000000000000000 &
b000010001110 (
b01010101011001100111011101010100 )
#722
#723
#724
#725
1$
b01010101011001100111011101010100 &
#726
#727
#728
#729
#730
0$
#731
b000010001111 %
b00000000000000000000000000000000 &
b000010001111 (
b01010101011001100111011101010110 )
#732
#733
#734
#735
1$
b01010101011001100111011101010110 &
#736
#737
#738
#739
#740
0$
#741
b000010010000 %
b00000000000000000000000000000000 &
b000010010000 (
b01010101011001100111011101011000 )
#742
#743
#744
#745
1$
b01010101011001100111011101011000 &
#746
#747
#748
#749
#750
0$
#751
b000010010001 %
b00000000000000000000000000000000 &
b000010010001 (
b01010101011001100111011101011010 )
#752
#753
#754
#755
1$
b01010101011001100111011101011010 &
#756
#757
#758
#759
#760
0$
#761
b000010010010 %
b00000000000000000000000000000000 &
b000010010010 (
b01010101011001100111011101011100 )
#762
#763
#764
#765
1$
b01010101011001100111011101011100 &
#766
#767
#768
#769
#770
0$
#771
b000010010011 %
b00000000000000000000000000000000 &
b000010010011 (
b01010101011001100111011101011110 )
#772
#773
#774
#775
1$
b01010101011001100111011101011110 &
#776
#777
#778
#779
#780
0$
#781
b000010010100 %
b00000000000000000000000000000000 &
b000010010100 (
b01010101011001100111011101100000 )
#782
#783
#784
#785
1$
b01010101011001100111011101100000 &
#786
#787
#788
#789
#790
0$
#791
b000010010101 %
b00000000000000000000000000000000 &
b000010010101 (
b01010101011001100111011101100010 )
#792
#793
#794
#795
1$
b01010101011001100111011101100010 &
#796
#797
#798
#799
#800
0$
#801
b000010010110 %
b00000000000000000000000000000000 &
b000010010110 (
b01010101011001100111011101100100 )
#802
#803
#804
#805
1$
b01010101011001100111011101100100 &
#806
#807
#808
#809
#810
0$
#811
b000010010111 %
b00000000000000000000000000000000 &
b000010010111 (
b01010101011001100111011101100110 )
#812
#813
#814
#815
1$
b01010101011001100111011101100110 &
#816
#817
#818
#819
#820
0$
#821
b000010011000 %
b00000000000000000000000000000000 &
b000010011000 (
b01010101011001100111011101101000 )
#822
#823
#824
#825
1$
b01010101011001100111011101101000 &
#826
#827
#828
#829
#830
0$
#831
b000010011001 %
b00000000000000000000000000000000 &
b000010011001 (
b01010101011001100111011101101010 )
#832
#833
#834
#835
1$
b01010101011001100111011101101010 &
#836
#837
#838
#839
#840
0$
#841
b000010011010 %
b00000000000000000000000000000000 &
b000010011010 (
b01010101011001100111011101101100 )
#842
#843
#844
#845
1$
b01010101011001100111011101101100 &
#846
#847
#848
#849
#850
0$
#851
b000010011011 %
b00000000000000000000000000000000 &
b000010011011 (
b01010101011001100111011101101110 )
#852
#853
#854
#855
1$
b01010101011001100111011101101110 &
#856
#857
#858
#859
#860
0$
#861
b000010011100 %
b00000000000000000000000000000000 &
b000010011100 (
b01010101011001100111011101110000 )
#862
#863
#864
#865
1$
b01010101011001100111011101110000 &
#866
#867
#868
#869
#870
0$
#871
b000010011101 %
b00000000000000000000000000000000 &
b000010011101 (
b01010101011001100111011101110010 )
#872
#873
#874
#875
1$
b01010101011001100111011101110010 &
#876
#877
#878
#879
#880
0$
#881
b000010011110 %
b00000000000000000000000000000000 &
b000010011110 (
b01010101011001100111011101110100 )
#882
#883
#884
#885
1$
b01010101011001100111011101110100 &
#886
#887
#888
#889
#890
0$
#891
b000010011111 %
b00000000000000000000000000000000 &
b000010011111 (
b01010101011001100111011101110110 )
#892
#893
#894
#895
1$
b01010101011001100111011101110110 &
#896
#897
#898
#899
#900
0$
#901
b000010100000 %
b00000000000000000000000000000000 &
b000010100000 (
b01010101011001100111011101111000 )
#902
#903
#904
#905
1$
b01010101011001100111011101111000 &
#906
#907
#908
#909
#910
0$
#911
b000010100001 %
b00000000000000000000000000000000 &
b000010100001 (
b01010101011001100111011101111010 )
#912
#913
#914
#915
1$
b01010101011001100111011101111010 &
#916
#917
#918
#919
#920
0$
#921
b000010100010 %
b00000000000000000000000000000000 &
b000010100010 (
b01010101011001100111011101111100 )
#922
#923
#924
#925
1$
b01010101011001100111011101111100 &
#926
#927
#928
#929
#930
0$
#931
b000010100011 %
b00000000000000000000000000000000 &
b000010100011 (
b01010101011001100111011101111110 )
#932
#933
#934
#935
1$
b01010101011001100111011101111110 &
#936
#937
#938
#939
#940
0$
#941
b000010100100 %
b00000000000000000000000000000000 &
b000010100100 (
b01010101011001100111011110000000 )
#942
#943
#944
#945
1$
b01010101011001100111011110000000 &
#946
#947
#948
#949
#950
0$
#951
b000010100101 %
b00000000000000000000000000000000 &
b000010100101 (
b01010101011001100111011110000010 )
#952
#953
#954
#955
1$
b01010101011001100111011110000010 &
#956
#957
#958
#959
#960
0$
#961
b000010100110 %
b00000000000000000000000000000000 &
b000010100110 (
b01010101011001100111011110000100 )
#962
#963
#964
#965
1$
b01010101011001100111011110000100 &
#966
#967
#968
#969
#970
0$
#971
b000010100111 %
b00000000000000000000000000000000 &
b000010100111 (
b01010101011001100111011110000110 )
#972
#973
#974
#975
1$
b01010101011001100111011110000110 &
#976
#977
#978
#979
#980
0$
#981
b000010101000 %
b00000000000000000000000000000000 &
b000010101000 (
b01010101011001100111011110001000 )
#982
#983
#984
#985
1$
b01010101011001100111011110001000 &
#986
#987
#988
#989
#990
0$
#991
b000010101001 %
b00000000000000000000000000000000 &
b000010101001 (
b01010101011001100111011110001010 )
#992
#993
#994
#995
1$
b01010101011001100111011110001010 &
