code/oscpu-my/cpu/defines.v

`timescale 1ns / 1ps

`define ZERO_WORD  64'h00000000_00000000
`define REG_BUS    63 : 0
`define INST_ADDI  8'h11

code/oscpu-my/cpu/regfile.v
/*
	寄存器组

	逻辑比较简单：
	1. 有两个读取通道（一般常用来表示：源操作数1，源操作数2），一个写入通道（用来处理目的操作数）
	2. 读取是组合逻辑，只要使能便有数据
	3. 写入是时序逻辑，在时钟上升沿根据写入使能信号写入数据
*/

`include "defines.v"

module regfile(clk,
               rst,
               w_addr,
               w_data,
               w_ena,
               r_addr1,
               r_data1,
               r_ena1,
               r_addr2,
               r_data2,
               r_ena2);
    input wire clk;
    input wire rst;
	// 寄存器写入通道
    input wire [4 : 0] w_addr;
    input wire [`REG_BUS] w_data;
    input wire 		 w_ena;
	// 寄存器读取通道1
    input wire [4 : 0] r_addr1;
    output reg [`REG_BUS] r_data1;
    input wire 		 r_ena1;
	// 寄存器读取通道2
    input wire [4 : 0] r_addr2;
    output reg [`REG_BUS] r_data2;
    input wire 		 r_ena2;
    
    // 32 registers
    reg [`REG_BUS] 	regs[0 : 31];
    
	// 时钟上升沿：复位，写入寄存器
    always @(posedge clk)
    begin
        if (rst == 1'b1)
        begin
            regs[0]  <= `ZERO_DWORD;
            regs[1]  <= `ZERO_DWORD;
            regs[2]  <= `ZERO_DWORD;
            regs[3]  <= `ZERO_DWORD;
            regs[4]  <= `ZERO_DWORD;
            regs[5]  <= `ZERO_DWORD;
            regs[6]  <= `ZERO_DWORD;
            regs[7]  <= `ZERO_DWORD;
            regs[8]  <= `ZERO_DWORD;
            regs[9]  <= `ZERO_DWORD;
            regs[10] <= `ZERO_DWORD;
            regs[11] <= `ZERO_DWORD;
            regs[12] <= `ZERO_DWORD;
            regs[13] <= `ZERO_DWORD;
            regs[14] <= `ZERO_DWORD;
            regs[15] <= `ZERO_DWORD;
            regs[16] <= `ZERO_DWORD;
            regs[17] <= `ZERO_DWORD;
            regs[18] <= `ZERO_DWORD;
            regs[19] <= `ZERO_DWORD;
            regs[20] <= `ZERO_DWORD;
            regs[21] <= `ZERO_DWORD;
            regs[22] <= `ZERO_DWORD;
            regs[23] <= `ZERO_DWORD;
            regs[24] <= `ZERO_DWORD;
            regs[25] <= `ZERO_DWORD;
            regs[26] <= `ZERO_DWORD;
            regs[27] <= `ZERO_DWORD;
            regs[28] <= `ZERO_DWORD;
            regs[29] <= `ZERO_DWORD;
            regs[30] <= `ZERO_DWORD;
            regs[31] <= `ZERO_DWORD;
        end
        else
        begin
			// 防止写入 r0
            if ((w_ena == 1'b1) && (w_addr != 5'h00)) begin
                regs[w_addr] <= w_data;
            end
        end
    end
    
	// 寄存器读取通道1
    always @(*) begin
        if (rst == 1'b1)
            r_data1 = `ZERO_DWORD;
        else if (r_ena1 == 1'b1)
            r_data1 = regs[r_addr1];
        else
            r_data1 = `ZERO_DWORD;
    end
    
	// 寄存器读取通道2
    always @(*) begin
        if (rst == 1'b1)
            r_data2 = `ZERO_DWORD;
        else if (r_ena2 == 1'b1)
            r_data2 = regs[r_addr2];
        else
            r_data2 = `ZERO_DWORD;
    end
    
endmodule

code/oscpu-framework-v1/cpu/exe_stage.v

//--xuezhen--

`include "defines.v"

module exe_stage(
  input wire rst,
  input wire [4 : 0]inst_type_i,
  input wire [7 : 0]inst_opcode,
  input wire [`REG_BUS]op1,
  input wire [`REG_BUS]op2,
  
  output wire [4 : 0]inst_type_o,
  output reg  [`REG_BUS]rd_data
);

assign inst_type_o = inst_type_i;

always@( * )
begin
  if( rst == 1'b1 )
  begin
    rd_data = `ZERO_WORD;
  end
  else
  begin
    case( inst_opcode )
	  `INST_ADDI: begin rd_data = op1 + op2;  end
	  default:    begin rd_data = `ZERO_WORD; end
	endcase
  end
end



endmodule

code/oscpu-my/cpu/id_stage.v

/* verilator lint_off UNDRIVEN */
/* verilator lint_off UNUSED */
//--xuezhen--

`include "defines.v"

module id_stage(
        rst,
        inst,
        rs1_data,
        rs2_data,
        rs1_r_ena,
        rs1_r_addr,
        rs2_r_ena,
        rs2_r_addr,
        rd_w_ena,
        rd_w_addr,
        inst_type,
        inst_opcode,
        op1,
        op2
    );

    input   wire                        rst;
    input   wire    [`INST_BUS ]        inst;           // 输入的指令
    input   wire    [`REG_BUS ]         rs1_data;       // 输入两个寄存器的值
    input   wire    [`REG_BUS ]         rs2_data;
    output  wire                        rs1_r_ena;
    output  wire    [4 : 0]             rs1_r_addr;
    output  wire                        rs2_r_ena;
    output  wire    [4 : 0]             rs2_r_addr;
    output  wire                        rd_w_ena;
    output  wire    [4 : 0]             rd_w_addr;
    output  wire    [4 : 0]             inst_type;
    output  wire    [7 : 0]             inst_opcode;
    output  wire    [`REG_BUS ]         op1;
    output  wire    [`REG_BUS ]         op2;
    
    // ===== 指令类型解析 =====
    
    // ---- 信号声明 ----

    // 公共部分
    wire [6 : 0]    opcode;
    wire op
    // R-type
    wire [5 : 0]    R_rs1,R_rs2,R_rd;
    wire [2 : 0]    R_funct3;
    wire [6 : 0]    R_funct7;
    // I-type
    wire [5 : 0]    I_rs1,R_rd;
    wire [2 : 0]    I_funct3;
    wire [11: 0]    I_imm;
    // S-type
    wire [5 : 0]    S_rs1,S_rs2;
    wire [2 : 0]    S_funct3;
    wire [11: 0]    S_imm;
    // B-type
    wire [5 : 0]    B_rs1,B_rs2;
    wire [2 : 0]    B_funct3;
    wire [11: 0]    B_imm;
    // U-type
    wire [5 : 0]    U_rd;
    wire [19: 0]    U_imm;
    // J-type
    wire [5 : 0]    J_rd;
    wire [19: 0]    J_imm;

    // ---- 信号定义 ----
    
    assign opcode   = inst[6 : 0];

    assign R_rs1    = inst[19:15];
    assign R_rs2    = inst[24:20];
    assign R_rd     = inst[11: 7];
    assign R_funct3 = inst[14:12];
    assign R_funct7 = inst[31:25];

    assign I_rs1    = inst[19:15];
    assign I_rd     = inst[11: 7];
    assign I_func3  = inst[14:12];
    assign I_imm    = inst[31:20];

    assign S_rs1    = inst[19:15];
    assign S_rs2    = inst[24:20];
    assign S_func3  = inst[14:12];
    assign S_imm    = {inst[31:25],inst[11:7]};

    assign B_rs1    = inst[19:15];
    assign B_rs2    = inst[24:20];
    assign B_func3  = inst[14:12];
    assign B_imm    = {inst[31:25],inst[11:7]};

    assign U_rd     = inst[11: 7];
    assign U_imm    = {inst[31:12]};

    assign J_rd     = inst[11: 7];
    assign J_imm    = {inst[31],inst[19:12],inst[20],inst[30:21]};

    // ===== 指令识别 =====
    
    wire inst_addi;

    assign inst_addi = ~opcode[2] & ~opcode[3] & opcode[4] & ~opcode[5] & ~opcode[6]
    & ~func3[0] & ~func3[1] & ~func3[2];
    
    // 根据指令，可判断是6种指令类型种的哪一种？

    // 确定指令类型、指令操作码

    // 10000    arith inst      算术运算
    // 01000    logic           逻辑运算
    // 00100    load-store      读写内存
    // 00010    j               是否跳转
    // 00001    sys             系统指令
    assign inst_type[4] = (rst == 1'b1) ? 0 : inst_addi;
    
    // 执行操作码（自定义的）
    // 8b0001_0001      addi
    // 8b....           其余指令
    // 由于 RV32I 由 47条， 。。。， 2^8=256条，足够保存了。
    assign inst_opcode[0] = (rst == 1'b1) ? 0 : inst_addi;
    assign inst_opcode[1] = (rst == 1'b1) ? 0 : 0;
    assign inst_opcode[2] = (rst == 1'b1) ? 0 : 0;
    assign inst_opcode[3] = (rst == 1'b1) ? 0 : 0;

    assign inst_opcode[4] = (rst == 1'b1) ? 0 : inst_addi;
    assign inst_opcode[5] = (rst == 1'b1) ? 0 : 0;
    assign inst_opcode[6] = (rst == 1'b1) ? 0 : 0;
    assign inst_opcode[7] = (rst == 1'b1) ? 0 : 0;
    
    
    assign rs1_r_ena  = (rst == 1'b1) ? 0 : inst_type[4];
    assign rs1_r_addr = (rst == 1'b1) ? 0 : (inst_type[4] == 1'b1 ? rs1 : 0);
    assign rs2_r_ena  = 0;
    assign rs2_r_addr = 0;
    
    assign rd_w_ena  = 0;// (rst == 1'b1) ? 0 : inst_type[4];
    assign rd_w_addr = (rst == 1'b1) ? 0 : (inst_type[4] == 1'b1 ? rd  : 0);
    
    assign op1 = (rst == 1'b1) ? 0 : (inst_type[4] == 1'b1 ? rs1_data : 0);
    assign op2 = (rst == 1'b1) ? 0 : (inst_type[4] == 1'b1 ? { {52{imm[11]}}, imm } : 0);
    
    
endmodule

code/oscpu-my/cpu/if_stage.v

/* verilator lint_off UNUSED */
//--xuezhen--

`include "defines.v"

module if_stage(input wire clk,
                input wire rst,
                output wire [63 : 0]inst_addr,
                output wire inst_ena);
    
    reg [`REG_BUS]pc;
    
    // fetch an instruction
    always@(posedge clk)
    begin
        if (rst == 1'b1)
        begin
            pc <= `ZERO_WORD ;
        end
        else
        begin
            pc <= pc + 4;
        end
    end
    
    assign inst_addr = pc;
    assign inst_ena  = (rst == 1'b1) ? 0 : 1;
    
    
endmodule

code/oscpu-my/cpu/rvcpu.v

/* verilator lint_off UNUSED */
//--xuezhen--

`timescale 1ns / 1ps

`include "defines.v"


module rvcpu(clk,
             rst,
             inst,
             inst_addr,
             inst_ena);
    
    input wire clk;
    input wire rst;
    /* ----- 模拟ROM ----- */
    // 输入的指令
    input wire [31 : 0] inst;
    
    /* ----- 调试? ----- */
    // 输出指令地址
    output wire [63 : 0] inst_addr;
    // 输出指令有效
    output wire inst_ena;
    
    /* ----- 内部信号 ----- */
    // 源操作数1
    wire rs1_r_ena;
    wire [4 : 0]rs1_r_addr;
    wire [`REG_BUS] r_data1;
    
    // 源操作数2
    wire rs2_r_ena;
    wire [4 : 0]rs2_r_addr;
    wire [`REG_BUS] r_data2;
    
    // 目的操作数
    wire rd_w_ena;
    wire [4 : 0]rd_w_addr;
    wire [`REG_BUS]rd_data;
    
    // 指令类型（自定义）（用于CU）
    wire [4 : 0]inst_type;
    // 指令操作（自定义）（用于ALU）
    wire [7 : 0]inst_opcode;
    
    // 操作数1，操作数2
    wire [`REG_BUS]op1;
    wire [`REG_BUS]op2;
    
    // exe_stage -> other stage
    wire [4 : 0]inst_type_o;
    // exe_stage -> regfile
    
    /* ----- 业务逻辑 ----- */

    if_stage If_stage(
    .clk(clk),
    .rst(rst),
    
    .inst_addr(inst_addr),
    .inst_ena(inst_ena)
    );
    
    id_stage Id_stage(
    .rst(rst),
    .inst(inst),
    .rs1_data(r_data1),
    .rs2_data(r_data2),
    
    .rs1_r_ena(rs1_r_ena),
    .rs1_r_addr(rs1_r_addr),
    .rs2_r_ena(rs2_r_ena),
    .rs2_r_addr(rs2_r_addr),
    .rd_w_ena(rd_w_ena),
    .rd_w_addr(rd_w_addr),
    .inst_type(inst_type),
    .inst_opcode(inst_opcode),
    .op1(op1),
    .op2(op2)
    );
    
    exe_stage Exe_stage(
    .rst(rst),
    .inst_type_i(inst_type),
    .inst_opcode(inst_opcode),
    .op1(op1),
    .op2(op2),
    
    .inst_type_o(inst_type_o),
    .rd_data(rd_data)
    );
    
    regfile Regfile(
    .clk(clk),
    .rst(rst),
    .w_addr(rd_w_addr),
    .w_data(rd_data),
    .w_ena(rd_w_ena),
    
    .r_addr1(rs1_r_addr),
    .r_data1(r_data1),
    .r_ena1(rs1_r_ena),
    .r_addr2(rs2_r_addr),
    .r_data2(r_data2),
    .r_ena2(rs2_r_ena)
    );
    
endmodule

code/oscpu-v1/cpu/build/top.vcd
$version Generated by VerilatedVcd $end
$date Sat Aug 14 22:18:09 2021 $end
$timescale 1ps $end

 $scope module TOP $end
  $var wire  1 i clk $end
  $var wire 32 k inst [31:0] $end
  $var wire 64 l inst_addr [63:0] $end
  $var wire  1 n inst_ena $end
  $var wire  1 j rst $end
  $scope module rvcpu $end
   $var wire  1 i clk $end
   $var wire 32 k inst [31:0] $end
   $var wire 64 l inst_addr [63:0] $end
   $var wire  1 n inst_ena $end
   $var wire  8 % inst_opcode [7:0] $end
   $var wire  5 $ inst_type [4:0] $end
   $var wire  5 $ inst_type_o [4:0] $end
   $var wire 64 q op1 [63:0] $end
   $var wire 64 s op2 [63:0] $end
   $var wire 64 u r_data1 [63:0] $end
   $var wire 64 "! r_data2 [63:0] $end
   $var wire 64 w rd_data [63:0] $end
   $var wire  5 # rd_w_addr [4:0] $end
   $var wire  1 o rd_w_ena $end
   $var wire  5 p rs1_r_addr [4:0] $end
   $var wire  1 o rs1_r_ena $end
   $var wire  5 !! rs2_r_addr [4:0] $end
   $var wire  1 ~ rs2_r_ena $end
   $var wire  1 j rst $end
   $scope module Exe_stage $end
    $var wire  8 % inst_opcode [7:0] $end
    $var wire  5 $ inst_type_i [4:0] $end
    $var wire  5 $ inst_type_o [4:0] $end
    $var wire 64 q op1 [63:0] $end
    $var wire 64 s op2 [63:0] $end
    $var wire 64 w rd_data [63:0] $end
    $var wire  1 j rst $end
   $upscope $end
   $scope module Id_stage $end
    $var wire  3 { func3 [2:0] $end
    $var wire 12 } imm [11:0] $end
    $var wire 32 k inst [31:0] $end
    $var wire  1 & inst_addi $end
    $var wire  8 % inst_opcode [7:0] $end
    $var wire  5 $ inst_type [4:0] $end
    $var wire 64 q op1 [63:0] $end
    $var wire 64 s op2 [63:0] $end
    $var wire  7 y opcode [6:0] $end
    $var wire  5 z rd [4:0] $end
    $var wire  5 # rd_w_addr [4:0] $end
    $var wire  1 o rd_w_ena $end
    $var wire  5 | rs1 [4:0] $end
    $var wire 64 u rs1_data [63:0] $end
    $var wire  5 p rs1_r_addr [4:0] $end
    $var wire  1 o rs1_r_ena $end
    $var wire 64 "! rs2_data [63:0] $end
    $var wire  5 !! rs2_r_addr [4:0] $end
    $var wire  1 ~ rs2_r_ena $end
    $var wire  1 j rst $end
   $upscope $end
   $scope module If_stage $end
    $var wire  1 i clk $end
    $var wire 64 l inst_addr [63:0] $end
    $var wire  1 n inst_ena $end
    $var wire 64 ' pc [63:0] $end
    $var wire  1 j rst $end
   $upscope $end
   $scope module Regfile $end
    $var wire  1 i clk $end
    $var wire  5 p r_addr1 [4:0] $end
    $var wire  5 !! r_addr2 [4:0] $end
    $var wire 64 u r_data1 [63:0] $end
    $var wire 64 "! r_data2 [63:0] $end
    $var wire  1 o r_ena1 $end
    $var wire  1 ~ r_ena2 $end
    $var wire 64 ) regs(0) [63:0] $end
    $var wire 64 + regs(1) [63:0] $end
    $var wire 64 = regs(10) [63:0] $end
    $var wire 64 ? regs(11) [63:0] $end
    $var wire 64 A regs(12) [63:0] $end
    $var wire 64 C regs(13) [63:0] $end
    $var wire 64 E regs(14) [63:0] $end
    $var wire 64 G regs(15) [63:0] $end
    $var wire 64 I regs(16) [63:0] $end
    $var wire 64 K regs(17) [63:0] $end
    $var wire 64 M regs(18) [63:0] $end
    $var wire 64 O regs(19) [63:0] $end
    $var wire 64 - regs(2) [63:0] $end
    $var wire 64 Q regs(20) [63:0] $end
    $var wire 64 S regs(21) [63:0] $end
    $var wire 64 U regs(22) [63:0] $end
    $var wire 64 W regs(23) [63:0] $end
    $var wire 64 Y regs(24) [63:0] $end
    $var wire 64 [ regs(25) [63:0] $end
    $var wire 64 ] regs(26) [63:0] $end
    $var wire 64 _ regs(27) [63:0] $end
    $var wire 64 a regs(28) [63:0] $end
    $var wire 64 c regs(29) [63:0] $end
    $var wire 64 / regs(3) [63:0] $end
    $var wire 64 e regs(30) [63:0] $end
    $var wire 64 g regs(31) [63:0] $end
    $var wire 64 1 regs(4) [63:0] $end
    $var wire 64 3 regs(5) [63:0] $end
    $var wire 64 5 regs(6) [63:0] $end
    $var wire 64 7 regs(7) [63:0] $end
    $var wire 64 9 regs(8) [63:0] $end
    $var wire 64 ; regs(9) [63:0] $end
    $var wire  1 j rst $end
    $var wire  5 # w_addr [4:0] $end
    $var wire 64 w w_data [63:0] $end
    $var wire  1 o w_ena $end
   $upscope $end
  $upscope $end
 $upscope $end
$enddefinitions $end


#0
b00000 #
b00000 $
b00000000 %
0&
b0000000000000000000000000000000000000000000000000000000000000000 '
b0000000000000000000000000000000000000000000000000000000000000000 )
b0000000000000000000000000000000000000000000000000000000000000000 +
b0000000000000000000000000000000000000000000000000000000000000000 -
b0000000000000000000000000000000000000000000000000000000000000000 /
b0000000000000000000000000000000000000000000000000000000000000000 1
b0000000000000000000000000000000000000000000000000000000000000000 3
b0000000000000000000000000000000000000000000000000000000000000000 5
b0000000000000000000000000000000000000000000000000000000000000000 7
b0000000000000000000000000000000000000000000000000000000000000000 9
b0000000000000000000000000000000000000000000000000000000000000000 ;
b0000000000000000000000000000000000000000000000000000000000000000 =
b0000000000000000000000000000000000000000000000000000000000000000 ?
b0000000000000000000000000000000000000000000000000000000000000000 A
b0000000000000000000000000000000000000000000000000000000000000000 C
b0000000000000000000000000000000000000000000000000000000000000000 E
b0000000000000000000000000000000000000000000000000000000000000000 G
b0000000000000000000000000000000000000000000000000000000000000000 I
b0000000000000000000000000000000000000000000000000000000000000000 K
b0000000000000000000000000000000000000000000000000000000000000000 M
b0000000000000000000000000000000000000000000000000000000000000000 O
b0000000000000000000000000000000000000000000000000000000000000000 Q
b0000000000000000000000000000000000000000000000000000000000000000 S
b0000000000000000000000000000000000000000000000000000000000000000 U
b0000000000000000000000000000000000000000000000000000000000000000 W
b0000000000000000000000000000000000000000000000000000000000000000 Y
b0000000000000000000000000000000000000000000000000000000000000000 [
b0000000000000000000000000000000000000000000000000000000000000000 ]
b0000000000000000000000000000000000000000000000000000000000000000 _
b0000000000000000000000000000000000000000000000000000000000000000 a
b0000000000000000000000000000000000000000000000000000000000000000 c
b0000000000000000000000000000000000000000000000000000000000000000 e
b0000000000000000000000000000000000000000000000000000000000000000 g
0i
1j
b00000000000000000000000000000000 k
b0000000000000000000000000000000000000000000000000000000000000000 l
0n
0o
b00000 p
b0000000000000000000000000000000000000000000000000000000000000000 q
b0000000000000000000000000000000000000000000000000000000000000000 s
b0000000000000000000000000000000000000000000000000000000000000000 u
b0000000000000000000000000000000000000000000000000000000000000000 w
b0000000 y
b00000 z
b000 {
b00000 |
b000000000000 }
0~
b00000 !!
b0000000000000000000000000000000000000000000000000000000000000000 "!
#1
#2
#3
#4
#5
1i
#6
#7
#8
#9
#10
0i
0j
1n
#11
#12
#13
#14
#15
b00001 #
b10000 $
b00010001 %
1&
b0000000000000000000000000000000000000000000000000000000000000100 '
1i
b00000000000100000000000010010011 k
b0000000000000000000000000000000000000000000000000000000000000100 l
1o
b0000000000000000000000000000000000000000000000000000000000000001 s
b0000000000000000000000000000000000000000000000000000000000000001 w
b0010011 y
b00001 z
b000000000001 }
#16
#17
#18
#19
#20
0i
#21
#22
#23
#24
#25
b0000000000000000000000000000000000000000000000000000000000001000 '
b0000000000000000000000000000000000000000000000000000000000000001 +
1i
b00000000001000000000000010010011 k
b0000000000000000000000000000000000000000000000000000000000001000 l
b0000000000000000000000000000000000000000000000000000000000000010 s
b0000000000000000000000000000000000000000000000000000000000000010 w
b000000000010 }
#26
#27
#28
#29
#30
0i
#31
#32
#33
#34
#35
b0000000000000000000000000000000000000000000000000000000000001100 '
b0000000000000000000000000000000000000000000000000000000000000010 +
1i
b00000000000100001000000010010011 k
b0000000000000000000000000000000000000000000000000000000000001100 l
b00001 p
b0000000000000000000000000000000000000000000000000000000000000010 q
b0000000000000000000000000000000000000000000000000000000000000001 s
b0000000000000000000000000000000000000000000000000000000000000010 u
b0000000000000000000000000000000000000000000000000000000000000011 w
b00001 |
b000000000001 }
#36
#37
#38
#39
#40
0i
#41
#42
#43
#44
#45
b00000 #
b00000 $
b00000000 %
0&
b0000000000000000000000000000000000000000000000000000000000010000 '
b0000000000000000000000000000000000000000000000000000000000000011 +
1i
b00000000000000000000000000000000 k
b0000000000000000000000000000000000000000000000000000000000010000 l
0o
b00000 p
b0000000000000000000000000000000000000000000000000000000000000000 q
b0000000000000000000000000000000000000000000000000000000000000000 s
b0000000000000000000000000000000000000000000000000000000000000000 u
b0000000000000000000000000000000000000000000000000000000000000000 w
b0000000 y
b00000 z
b00000 |
b000000000000 }
#46
#47
#48
#49
#50
0i
#51
#52
#53
#54
#55
b0000000000000000000000000000000000000000000000000000000000010100 '
1i
b0000000000000000000000000000000000000000000000000000000000010100 l
#56
#57
#58
#59
#60
0i
#61
#62
#63
#64
#65
b0000000000000000000000000000000000000000000000000000000000011000 '
1i
b0000000000000000000000000000000000000000000000000000000000011000 l
#66
#67
#68
#69
#70
0i
#71
#72
#73
#74
#75
b0000000000000000000000000000000000000000000000000000000000011100 '
1i
b0000000000000000000000000000000000000000000000000000000000011100 l
#76
#77
#78
#79
#80
0i
#81
#82
#83
#84
#85
b0000000000000000000000000000000000000000000000000000000000100000 '
1i
b0000000000000000000000000000000000000000000000000000000000100000 l
#86
#87
#88
#89
#90
0i
#91
#92
#93
#94
#95
b0000000000000000000000000000000000000000000000000000000000100100 '
1i
b0000000000000000000000000000000000000000000000000000000000100100 l
#96
#97
#98
#99
#100
0i
#101
#102
#103
#104
#105
b0000000000000000000000000000000000000000000000000000000000101000 '
1i
b0000000000000000000000000000000000000000000000000000000000101000 l
#106
#107
#108
#109
#110
0i
#111
#112
#113
#114
#115
b0000000000000000000000000000000000000000000000000000000000101100 '
1i
b0000000000000000000000000000000000000000000000000000000000101100 l
#116
#117
#118
#119
#120
0i
#121
#122
#123
#124
#125
b0000000000000000000000000000000000000000000000000000000000110000 '
1i
b0000000000000000000000000000000000000000000000000000000000110000 l
#126
#127
#128
#129
#130
0i
#131
#132
#133
#134
#135
b0000000000000000000000000000000000000000000000000000000000110100 '
1i
b0000000000000000000000000000000000000000000000000000000000110100 l
#136
#137
#138
#139
#140
0i
#141
#142
#143
#144
#145
b0000000000000000000000000000000000000000000000000000000000111000 '
1i
b0000000000000000000000000000000000000000000000000000000000111000 l
#146
#147
#148
#149
#150
0i
#151
#152
#153
#154
#155
b0000000000000000000000000000000000000000000000000000000000111100 '
1i
b0000000000000000000000000000000000000000000000000000000000111100 l
#156
#157
#158
#159
#160
0i
#161
#162
#163
#164
#165
b0000000000000000000000000000000000000000000000000000000001000000 '
1i
b0000000000000000000000000000000000000000000000000000000001000000 l
#166
#167
#168
#169
#170
0i
#171
#172
#173
#174
#175
b0000000000000000000000000000000000000000000000000000000001000100 '
1i
b0000000000000000000000000000000000000000000000000000000001000100 l
#176
#177
#178
#179
#180
0i
#181
#182
#183
#184
#185
b0000000000000000000000000000000000000000000000000000000001001000 '
1i
b0000000000000000000000000000000000000000000000000000000001001000 l
#186
#187
#188
#189
#190
0i
#191
#192
#193
#194
#195
b0000000000000000000000000000000000000000000000000000000001001100 '
1i
b0000000000000000000000000000000000000000000000000000000001001100 l
#196
#197
#198
#199
#200
0i
#201
#202
#203
#204
#205
b0000000000000000000000000000000000000000000000000000000001010000 '
1i
b0000000000000000000000000000000000000000000000000000000001010000 l
#206
#207
#208
#209
#210
0i
#211
#212
#213
#214
#215
b0000000000000000000000000000000000000000000000000000000001010100 '
1i
b0000000000000000000000000000000000000000000000000000000001010100 l
#216
#217
#218
#219
#220
0i
#221
#222
#223
#224
#225
b0000000000000000000000000000000000000000000000000000000001011000 '
1i
b0000000000000000000000000000000000000000000000000000000001011000 l
#226
#227
#228
#229
#230
0i
#231
#232
#233
#234
#235
b0000000000000000000000000000000000000000000000000000000001011100 '
1i
b0000000000000000000000000000000000000000000000000000000001011100 l
#236
#237
#238
#239
#240
0i
#241
#242
#243
#244
#245
b0000000000000000000000000000000000000000000000000000000001100000 '
1i
b0000000000000000000000000000000000000000000000000000000001100000 l
#246
#247
#248
#249
#250
0i
#251
#252
#253
#254
#255
b0000000000000000000000000000000000000000000000000000000001100100 '
1i
b0000000000000000000000000000000000000000000000000000000001100100 l
#256
#257
#258
#259
#260
0i
#261
#262
#263
#264
#265
b0000000000000000000000000000000000000000000000000000000001101000 '
1i
b0000000000000000000000000000000000000000000000000000000001101000 l
#266
#267
#268
#269
#270
0i
#271
#272
#273
#274
#275
b0000000000000000000000000000000000000000000000000000000001101100 '
1i
b0000000000000000000000000000000000000000000000000000000001101100 l
#276
#277
#278
#279
#280
0i
#281
#282
#283
#284
#285
b0000000000000000000000000000000000000000000000000000000001110000 '
1i
b0000000000000000000000000000000000000000000000000000000001110000 l
#286
#287
#288
#289
#290
0i
#291
#292
#293
#294
#295
b0000000000000000000000000000000000000000000000000000000001110100 '
1i
b0000000000000000000000000000000000000000000000000000000001110100 l
#296
#297
#298
#299
#300
0i
#301
#302
#303
#304
#305
b0000000000000000000000000000000000000000000000000000000001111000 '
1i
b0000000000000000000000000000000000000000000000000000000001111000 l
#306
#307
#308
#309
#310
0i
#311
#312
#313
#314
#315
b0000000000000000000000000000000000000000000000000000000001111100 '
1i
b0000000000000000000000000000000000000000000000000000000001111100 l
#316
#317
#318
#319
#320
0i
#321
#322
#323
#324
#325
b0000000000000000000000000000000000000000000000000000000010000000 '
1i
b0000000000000000000000000000000000000000000000000000000010000000 l
#326
#327
#328
#329
#330
0i
#331
#332
#333
#334
#335
b0000000000000000000000000000000000000000000000000000000010000100 '
1i
b0000000000000000000000000000000000000000000000000000000010000100 l
#336
#337
#338
#339
#340
0i
#341
#342
#343
#344
#345
b0000000000000000000000000000000000000000000000000000000010001000 '
1i
b0000000000000000000000000000000000000000000000000000000010001000 l
#346
#347
#348
#349
#350
0i
#351
#352
#353
#354
#355
b0000000000000000000000000000000000000000000000000000000010001100 '
1i
b0000000000000000000000000000000000000000000000000000000010001100 l
#356
#357
#358
#359
#360
0i
#361
#362
#363
#364
#365
b0000000000000000000000000000000000000000000000000000000010010000 '
1i
b0000000000000000000000000000000000000000000000000000000010010000 l
#366
#367
#368
#369
#370
0i
#371
#372
#373
#374
#375
b0000000000000000000000000000000000000000000000000000000010010100 '
1i
b0000000000000000000000000000000000000000000000000000000010010100 l
#376
#377
#378
#379
#380
0i
#381
#382
#383
#384
#385
b0000000000000000000000000000000000000000000000000000000010011000 '
1i
b0000000000000000000000000000000000000000000000000000000010011000 l
#386
#387
#388
#389
#390
0i
#391
#392
#393
#394
#395
b0000000000000000000000000000000000000000000000000000000010011100 '
1i
b0000000000000000000000000000000000000000000000000000000010011100 l
#396
#397
#398
#399
#400
0i
#401
#402
#403
#404
#405
b0000000000000000000000000000000000000000000000000000000010100000 '
1i
b0000000000000000000000000000000000000000000000000000000010100000 l
#406
#407
#408
#409
#410
0i
#411
#412
#413
#414
#415
b0000000000000000000000000000000000000000000000000000000010100100 '
1i
b0000000000000000000000000000000000000000000000000000000010100100 l
#416
#417
#418
#419
#420
0i
#421
#422
#423
#424
#425
b0000000000000000000000000000000000000000000000000000000010101000 '
1i
b0000000000000000000000000000000000000000000000000000000010101000 l
#426
#427
#428
#429
#430
0i
#431
#432
#433
#434
#435
b0000000000000000000000000000000000000000000000000000000010101100 '
1i
b0000000000000000000000000000000000000000000000000000000010101100 l
#436
#437
#438
#439
#440
0i
#441
#442
#443
#444
#445
b0000000000000000000000000000000000000000000000000000000010110000 '
1i
b0000000000000000000000000000000000000000000000000000000010110000 l
#446
#447
#448
#449
#450
0i
#451
#452
#453
#454
#455
b0000000000000000000000000000000000000000000000000000000010110100 '
1i
b0000000000000000000000000000000000000000000000000000000010110100 l
#456
#457
#458
#459
#460
0i
#461
#462
#463
#464
#465
b0000000000000000000000000000000000000000000000000000000010111000 '
1i
b0000000000000000000000000000000000000000000000000000000010111000 l
#466
#467
#468
#469
#470
0i
#471
#472
#473
#474
#475
b0000000000000000000000000000000000000000000000000000000010111100 '
1i
b0000000000000000000000000000000000000000000000000000000010111100 l
#476
#477
#478
#479
#480
0i
#481
#482
#483
#484
#485
b0000000000000000000000000000000000000000000000000000000011000000 '
1i
b0000000000000000000000000000000000000000000000000000000011000000 l
#486
#487
#488
#489
#490
0i
#491
#492
#493
#494
#495
b0000000000000000000000000000000000000000000000000000000011000100 '
1i
b0000000000000000000000000000000000000000000000000000000011000100 l
#496
#497
#498
#499
#500
0i
#501
#502
#503
#504
#505
b0000000000000000000000000000000000000000000000000000000011001000 '
1i
b0000000000000000000000000000000000000000000000000000000011001000 l
#506
#507
#508
#509
#510
0i
#511
#512
#513
#514
#515
b0000000000000000000000000000000000000000000000000000000011001100 '
1i
b0000000000000000000000000000000000000000000000000000000011001100 l
#516
#517
#518
#519
#520
0i
#521
#522
#523
#524
#525
b0000000000000000000000000000000000000000000000000000000011010000 '
1i
b0000000000000000000000000000000000000000000000000000000011010000 l
#526
#527
#528
#529
#530
0i
#531
#532
#533
#534
#535
b0000000000000000000000000000000000000000000000000000000011010100 '
1i
b0000000000000000000000000000000000000000000000000000000011010100 l
#536
#537
#538
#539
#540
0i
#541
#542
#543
#544
#545
b0000000000000000000000000000000000000000000000000000000011011000 '
1i
b0000000000000000000000000000000000000000000000000000000011011000 l
#546
#547
#548
#549
#550
0i
#551
#552
#553
#554
#555
b0000000000000000000000000000000000000000000000000000000011011100 '
1i
b0000000000000000000000000000000000000000000000000000000011011100 l
#556
#557
#558
#559
#560
0i
#561
#562
#563
#564
#565
b0000000000000000000000000000000000000000000000000000000011100000 '
1i
b0000000000000000000000000000000000000000000000000000000011100000 l
#566
#567
#568
#569
#570
0i
#571
#572
#573
#574
#575
b0000000000000000000000000000000000000000000000000000000011100100 '
1i
b0000000000000000000000000000000000000000000000000000000011100100 l
#576
#577
#578
#579
#580
0i
#581
#582
#583
#584
#585
b0000000000000000000000000000000000000000000000000000000011101000 '
1i
b0000000000000000000000000000000000000000000000000000000011101000 l
#586
#587
#588
#589
#590
0i
#591
#592
#593
#594
#595
b0000000000000000000000000000000000000000000000000000000011101100 '
1i
b0000000000000000000000000000000000000000000000000000000011101100 l
#596
#597
#598
#599
#600
0i
#601
#602
#603
#604
#605
b0000000000000000000000000000000000000000000000000000000011110000 '
1i
b0000000000000000000000000000000000000000000000000000000011110000 l
#606
#607
#608
#609
#610
0i
#611
#612
#613
#614
