code/learn/verilog_examples/03_counter/counter/counter4_10.v
// 模值可变计数器
module mchange_1(q,clk,clr,m);
output [7:0] q;         // 数据输出
input clk,clr;          // 时钟，复位
input [7:0] m;          // 模值
reg [7:0] q;
reg [7:0] md;           // 模值-1

always @(posedge clk) begin
    md <= m - 1;
    if (clr)
        q <= 0;
    else begin
        if (q == md)
            q <= 0;
        else
            q <= q + 1;
    end
end

endmodule

code/learn/verilog_examples/03_counter/counter/counter4_10_tb.v
// 仿真程序
`timescale 1ns/1ns
`include "counter4_10.v"
module counter4_10_tb;
reg clk,clr;        // 时钟、复位
reg [7:0] m;        // 模值
wire [7:0] q;       // 输出
parameter DELAY = 20;

mchange_1 uc(q,clk,clr,m);

always #(DELAY/2) clk = ~clk;

initial begin
            m = 10; clk = 0; clr = 0;
    // 模拟 clr 信号
    #DELAY  clr = 1;
    #DELAY  clr = 0;
    // 模拟 不同的模值
    #(DELAY*20) m = 20;
    #(DELAY*40) m = 30;
    #(DELAY*50) $finish;
end

// 打印信号
initial 
    $monitor($time, ": clk=%b clr=%b m=%d q=%d", 
        clk,clr,m,q);

// 生成vcd波形文件
initial begin
    $dumpfile("./build/counter4_10_wave.vcd");
    $dumpvars(0, counter4_10_tb);  // 指定层次数为0，顶层模块为 xx
end

endmodule

code/learn/verilog_examples/03_counter/counter/build/counter4_10_wave.vcd
$date
	Wed Aug 04 17:02:03 2021
$end
$version
	Icarus Verilog
$end
$timescale
	1ns
$end
$scope module counter4_10_tb $end
$var wire 8 ! q [7:0] $end
$var reg 1 " clk $end
$var reg 1 # clr $end
$var reg 8 $ m [7:0] $end
$scope module uc $end
$var wire 1 " clk $end
$var wire 1 # clr $end
$var wire 8 % m [7:0] $end
$var reg 8 & md [7:0] $end
$var reg 8 ' q [7:0] $end
$upscope $end
$upscope $end
$enddefinitions $end
#0
$dumpvars
bx '
bx &
b1010 %
b1010 $
0#
0"
bx !
$end
#10
b1001 &
1"
#20
0"
1#
#30
b0 !
b0 '
1"
#40
0"
0#
#50
b1 !
b1 '
1"
#60
0"
#70
b10 !
b10 '
1"
#80
0"
#90
b11 !
b11 '
1"
#100
0"
#110
b100 !
b100 '
1"
#120
0"
#130
b101 !
b101 '
1"
#140
0"
#150
b110 !
b110 '
1"
#160
0"
#170
b111 !
b111 '
1"
#180
0"
#190
b1000 !
b1000 '
1"
#200
0"
#210
b1001 !
b1001 '
1"
#220
0"
#230
b0 !
b0 '
1"
#240
0"
#250
b1 !
b1 '
1"
#260
0"
#270
b10 !
b10 '
1"
#280
0"
#290
b11 !
b11 '
1"
#300
0"
#310
b100 !
b100 '
1"
#320
0"
#330
b101 !
b101 '
1"
#340
0"
#350
b110 !
b110 '
1"
#360
0"
#370
b111 !
b111 '
1"
#380
0"
#390
b1000 !
b1000 '
1"
#400
0"
#410
b1001 !
b1001 '
1"
#420
0"
#430
b0 !
b0 '
1"
#440
0"
b10100 $
b10100 %
#450
b1 !
b1 '
b10011 &
1"
#460
0"
#470
b10 !
b10 '
1"
#480
0"
#490
b11 !
b11 '
1"
#500
0"
#510
b100 !
b100 '
1"
#520
0"
#530
b101 !
b101 '
1"
#540
0"
#550
b110 !
b110 '
1"
#560
0"
#570
b111 !
b111 '
1"
#580
0"
#590
b1000 !
b1000 '
1"
#600
0"
#610
b1001 !
b1001 '
1"
#620
0"
#630
b1010 !
b1010 '
1"
#640
0"
#650
b1011 !
b1011 '
1"
#660
0"
#670
b1100 !
b1100 '
1"
#680
0"
#690
b1101 !
b1101 '
1"
#700
0"
#710
b1110 !
b1110 '
1"
#720
0"
#730
b1111 !
b1111 '
1"
#740
0"
#750
b10000 !
b10000 '
1"
#760
0"
#770
b10001 !
b10001 '
1"
#780
0"
#790
b10010 !
b10010 '
1"
#800
0"
#810
b10011 !
b10011 '
1"
#820
0"
#830
b0 !
b0 '
1"
#840
0"
#850
b1 !
b1 '
1"
#860
0"
#870
b10 !
b10 '
1"
#880
0"
#890
b11 !
b11 '
1"
#900
0"
#910
b100 !
b100 '
1"
#920
0"
#930
b101 !
b101 '
1"
#940
0"
#950
b110 !
b110 '
1"
#960
0"
#970
b111 !
b111 '
1"
#980
0"
#990
b1000 !
b1000 '
1"
#1000
0"
#1010
b1001 !
b1001 '
1"
#1020
0"
#1030
b1010 !
b1010 '
1"
#1040
0"
#1050
b1011 !
b1011 '
1"
#1060
0"
#1070
b1100 !
b1100 '
1"
#1080
0"
#1090
b1101 !
b1101 '
1"
#1100
0"
#1110
b1110 !
b1110 '
1"
#1120
0"
#1130
b1111 !
b1111 '
1"
#1140
0"
#1150
b10000 !
b10000 '
1"
#1160
0"
#1170
b10001 !
b10001 '
1"
#1180
0"
#1190
b10010 !
b10010 '
1"
#1200
0"
#1210
b10011 !
b10011 '
1"
#1220
0"
#1230
b0 !
b0 '
1"
#1240
0"
b11110 $
b11110 %
#1250
b1 !
b1 '
b11101 &
1"
#1260
0"
#1270
b10 !
b10 '
1"
#1280
0"
#1290
b11 !
b11 '
1"
#1300
0"
#1310
b100 !
b100 '
1"
#1320
0"
#1330
b101 !
b101 '
1"
#1340
0"
#1350
b110 !
b110 '
1"
#1360
0"
#1370
b111 !
b111 '
1"
#1380
0"
#1390
b1000 !
b1000 '
1"
#1400
0"
#1410
b1001 !
b1001 '
1"
#1420
0"
#1430
b1010 !
b1010 '
1"
#1440
0"
#1450
b1011 !
b1011 '
1"
#1460
0"
#1470
b1100 !
b1100 '
1"
#1480
0"
#1490
b1101 !
b1101 '
1"
#1500
0"
#1510
b1110 !
b1110 '
1"
#1520
0"
#1530
b1111 !
b1111 '
1"
#1540
0"
#1550
b10000 !
b10000 '
1"
#1560
0"
#1570
b10001 !
b10001 '
1"
#1580
0"
#1590
b10010 !
b10010 '
1"
#1600
0"
#1610
b10011 !
b10011 '
1"
#1620
0"
#1630
b10100 !
b10100 '
1"
#1640
0"
#1650
b10101 !
b10101 '
1"
#1660
0"
#1670
b10110 !
b10110 '
1"
#1680
0"
#1690
b10111 !
b10111 '
1"
#1700
0"
#1710
b11000 !
b11000 '
1"
#1720
0"
#1730
b11001 !
b11001 '
1"
#1740
0"
#1750
b11010 !
b11010 '
1"
#1760
0"
#1770
b11011 !
b11011 '
1"
#1780
0"
#1790
b11100 !
b11100 '
1"
#1800
0"
#1810
b11101 !
b11101 '
1"
#1820
0"
#1830
b0 !
b0 '
1"
#1840
0"
#1850
b1 !
b1 '
1"
#1860
0"
#1870
b10 !
b10 '
1"
#1880
0"
#1890
b11 !
b11 '
1"
#1900
0"
#1910
b100 !
b100 '
1"
#1920
0"
#1930
b101 !
b101 '
1"
#1940
0"
#1950
b110 !
b110 '
1"
#1960
0"
#1970
b111 !
b111 '
1"
#1980
0"
#1990
b1000 !
b1000 '
1"
#2000
0"
#2010
b1001 !
b1001 '
1"
#2020
0"
#2030
b1010 !
b1010 '
1"
#2040
0"
#2050
b1011 !
b1011 '
1"
#2060
0"
#2070
b1100 !
b1100 '
1"
#2080
0"
#2090
b1101 !
b1101 '
1"
#2100
0"
#2110
b1110 !
b1110 '
1"
#2120
0"
#2130
b1111 !
b1111 '
1"
#2140
0"
#2150
b10000 !
b10000 '
1"
#2160
0"
#2170
b10001 !
b10001 '
1"
#2180
0"
#2190
b10010 !
b10010 '
1"
#2200
0"
#2210
b10011 !
b10011 '
1"
#2220
0"
#2230
b10100 !
b10100 '
1"
