code/learn/verilog_examples/03_counter/counter/counter4_7.v
// 十进制模24计数器
module cnt24(ten,one,co,clk,clr);
output [3:0] ten,one;
output co;
input clk,clr;
reg [3:0] ten,one;
reg co;

always @(posedge clk) begin
    if (clr) begin
        ten <= 0; one <= 0; co <= 0;
    end
    else begin
        if ({ten,one} == 8'b0010_0011) begin
            ten <= 0; one <= 0; co <= 1;
        end
        else if (one == 4'b1001) begin
            ten <= ten + 1; one <= 0; co <= 0;
        end
        else begin
            one = one + 1; co <= 0;
        end
    end
end
endmodule

code/learn/verilog_examples/03_counter/counter/counter4_7_tb.v
// 4位计数器的仿真程序
`timescale 1ns/1ns
`include "counter4_7.v"
module counter4_7_tb;
reg clk,clr;
wire [3:0] ten,one;
wire co;
parameter DELAY = 20;

cnt24 uc(ten,one,co,clk,clr);

always #(DELAY/2) clk = ~clk;

initial begin
            clk = 0;
            clr = 0;
    #DELAY  clr = 1;
    #DELAY  clr = 0;
    #(DELAY*50)
            $finish;
end

// 打印信号
initial 
    $monitor($time, ": clr=%b clk=%b co=%d ten=%d one=%d", clr,clk,co,ten,one);

// 生成vcd波形文件
initial begin
    $dumpfile("./build/counter4_7_wave.vcd");
    $dumpvars(0, counter4_7_tb);  // 指定层次数为0，顶层模块为 counter4_tb
    #10000 $finish;
end

endmodule

code/learn/verilog_examples/03_counter/counter/build/counter4_7_wave.vcd
$date
	Wed Aug 04 11:59:07 2021
$end
$version
	Icarus Verilog
$end
$timescale
	1ns
$end
$scope module counter4_7_tb $end
$var wire 4 ! ten [3:0] $end
$var wire 4 " one [3:0] $end
$var wire 1 # co $end
$var reg 1 $ clk $end
$var reg 1 % clr $end
$scope module uc $end
$var wire 1 $ clk $end
$var wire 1 % clr $end
$var reg 1 # co $end
$var reg 4 & one [3:0] $end
$var reg 4 ' ten [3:0] $end
$upscope $end
$upscope $end
$enddefinitions $end
#0
$dumpvars
bx '
bx &
0%
0$
x#
bx "
bx !
$end
#10
0#
1$
#20
0$
1%
#30
b0 "
b0 &
b0 !
b0 '
1$
#40
0$
0%
#50
b1 "
b1 &
1$
#60
0$
#70
b10 "
b10 &
1$
#80
0$
#90
b11 "
b11 &
1$
#100
0$
#110
b100 "
b100 &
1$
#120
0$
#130
b101 "
b101 &
1$
#140
0$
#150
b110 "
b110 &
1$
#160
0$
#170
b111 "
b111 &
1$
#180
0$
#190
b1000 "
b1000 &
1$
#200
0$
#210
b1001 "
b1001 &
1$
#220
0$
#230
b0 "
b0 &
b1 !
b1 '
1$
#240
0$
#250
b1 "
b1 &
1$
#260
0$
#270
b10 "
b10 &
1$
#280
0$
#290
b11 "
b11 &
1$
#300
0$
#310
b100 "
b100 &
1$
#320
0$
#330
b101 "
b101 &
1$
#340
0$
#350
b110 "
b110 &
1$
#360
0$
#370
b111 "
b111 &
1$
#380
0$
#390
b1000 "
b1000 &
1$
#400
0$
#410
b1001 "
b1001 &
1$
#420
0$
#430
b0 "
b0 &
b10 !
b10 '
1$
#440
0$
#450
b1 "
b1 &
1$
#460
0$
#470
b10 "
b10 &
1$
#480
0$
#490
b11 "
b11 &
1$
#500
0$
#510
1#
b0 "
b0 &
b0 !
b0 '
1$
#520
0$
#530
0#
b1 "
b1 &
1$
#540
0$
#550
b10 "
b10 &
1$
#560
0$
#570
b11 "
b11 &
1$
#580
0$
#590
b100 "
b100 &
1$
#600
0$
#610
b101 "
b101 &
1$
#620
0$
#630
b110 "
b110 &
1$
#640
0$
#650
b111 "
b111 &
1$
#660
0$
#670
b1000 "
b1000 &
1$
#680
0$
#690
b1001 "
b1001 &
1$
#700
0$
#710
b0 "
b0 &
b1 !
b1 '
1$
#720
0$
#730
b1 "
b1 &
1$
#740
0$
#750
b10 "
b10 &
1$
#760
0$
#770
b11 "
b11 &
1$
#780
0$
#790
b100 "
b100 &
1$
#800
0$
#810
b101 "
b101 &
1$
#820
0$
#830
b110 "
b110 &
1$
#840
0$
#850
b111 "
b111 &
1$
#860
0$
#870
b1000 "
b1000 &
1$
#880
0$
#890
b1001 "
b1001 &
1$
#900
0$
#910
b0 "
b0 &
b10 !
b10 '
1$
#920
0$
#930
b1 "
b1 &
1$
#940
0$
#950
b10 "
b10 &
1$
#960
0$
#970
b11 "
b11 &
1$
#980
0$
#990
1#
b0 "
b0 &
b0 !
b0 '
1$
#1000
0$
#1010
0#
b1 "
b1 &
1$
#1020
0$
#1030
b10 "
b10 &
1$
