code/learn/verilog_examples/03_counter/counter/counter4_2.v
// 4位计数器

// 异步复位，电平触发，行为描述的
module counter4_2(out,clk,rst);
output [3:0] out;
input clk,rst;
reg [3:0] out;

always @(clk or rst) begin
    if (rst) out = 0;
    else out = out + 1;
end

endmodule

code/learn/verilog_examples/03_counter/counter/counter4_2_tb.v
// 4位计数器的仿真程序
`timescale 1ns/1ns
`include "counter4_2.v"
module counter4_2_tb;
reg clk,rst;
wire [3:0] out;
parameter DELAY = 20;

counter4_2 uc4(out,clk,rst);


always #(DELAY/2) clk = ~clk;

initial begin
            clk = 0; rst = 0;
    #DELAY  rst = 1;
    #DELAY  rst = 0;
    #(DELAY*20)
            $finish;
end

// 打印信号
initial 
    $monitor($time, ":rst=%b clk=%b out=%d", rst,clk,out);

// 生成vcd波形文件
initial begin
    $dumpfile("./build/counter4_2_wave.vcd");
    $dumpvars(0, counter4_2_tb);  // 指定层次数为0，顶层模块为 counter4_tb
    #10000 $finish;
end

endmodule

code/learn/verilog_examples/03_counter/counter/build/counter4_2_wave.vcd
$date
	Wed Aug 04 08:36:22 2021
$end
$version
	Icarus Verilog
$end
$timescale
	1ns
$end
$scope module counter4_2_tb $end
$var wire 4 ! out [3:0] $end
$var reg 1 " clk $end
$var reg 1 # rst $end
$scope module uc4 $end
$var wire 1 " clk $end
$var wire 1 # rst $end
$var reg 4 $ out [3:0] $end
$upscope $end
$upscope $end
$enddefinitions $end
#0
$dumpvars
bx $
0#
0"
bx !
$end
#10
1"
#20
b0 !
b0 $
0"
1#
#30
1"
#40
b1 !
b1 $
0"
0#
#50
b10 !
b10 $
1"
#60
b11 !
b11 $
0"
#70
b100 !
b100 $
1"
#80
b101 !
b101 $
0"
#90
b110 !
b110 $
1"
#100
b111 !
b111 $
0"
#110
b1000 !
b1000 $
1"
#120
b1001 !
b1001 $
0"
#130
b1010 !
b1010 $
1"
#140
b1011 !
b1011 $
0"
#150
b1100 !
b1100 $
1"
#160
b1101 !
b1101 $
0"
#170
b1110 !
b1110 $
1"
#180
b1111 !
b1111 $
0"
#190
b0 !
b0 $
1"
#200
b1 !
b1 $
0"
#210
b10 !
b10 $
1"
#220
b11 !
b11 $
0"
#230
b100 !
b100 $
1"
#240
b101 !
b101 $
0"
#250
b110 !
b110 $
1"
#260
b111 !
b111 $
0"
#270
b1000 !
b1000 $
1"
#280
b1001 !
b1001 $
0"
#290
b1010 !
b1010 $
1"
#300
b1011 !
b1011 $
0"
#310
b1100 !
b1100 $
1"
#320
b1101 !
b1101 $
0"
#330
b1110 !
b1110 $
1"
#340
b1111 !
b1111 $
0"
#350
b0 !
b0 $
1"
#360
b1 !
b1 $
0"
#370
b10 !
b10 $
1"
#380
b11 !
b11 $
0"
#390
b100 !
b100 $
1"
#400
b101 !
b101 $
0"
#410
b110 !
b110 $
1"
#420
b111 !
b111 $
0"
#430
b1000 !
b1000 $
1"
#440
b1001 !
b1001 $
0"
