code/learn/verilog_examples/03_counter/counter/counter4_8.v
// 模为60的BCD码加法计数器
module cnt60(qout,cout,data,load,cin,rst,clk);
output [7:0] qout;      // 数据输出
output cout;            // 进位标志
input [7:0] data;      // 初始数据
input load,cin,rst,clk; // 装填标志，进位输入，复位，时钟
reg [7:0] qout;

always @(posedge clk) begin
    if (rst)
        qout <= 0;      // 同步复位
    else if (load)
        qout <= data;   // 同步置位
    else if (cin) begin
        if (qout[3:0]===9) begin    // 低4位是否为9，是则
            qout[3:0] <= 0;     // 置0，并判断高4位是否为5
            if (qout[7:4] === 5)
                qout[7:4] <= 0;
            else
                qout[7:4] <= qout[7:4] + 1;
        end
        else    // 低4位不为9，则增加
            qout[3:0] <= qout[3:0] + 1;    
    end
end

assign cout = ((qout == 8'h59) & cin) ? 1 : 0;  // 产生进位输出信号

endmodule

code/learn/verilog_examples/03_counter/counter/counter4_8_tb.v
// 仿真程序
`timescale 1ns/1ns
`include "counter4_8.v"
module counter4_8_tb;
reg clk,rst,load,cin;       // 时钟、复位、装填、进位输入
reg [7:0] data;
wire [7:0] qout;
wire cout;
parameter DELAY = 20;

cnt60 uc(qout,cout,data,load,cin,rst,clk);

always #(DELAY/2) clk = ~clk;

// 模拟 cin 信号
always #(DELAY*5) cin = ~cin;

initial begin
            clk = 0; rst = 0; load = 0; cin = 0; data = 8'h24;
    #DELAY  rst = 1;
    #DELAY  rst = 0;
    #(DELAY*11) load = 1;   // 运行一阵子后，模拟load信号
    #DELAY  load = 0;
    #(DELAY*200) $finish;    // 常规计数时序
end

// 打印信号
initial 
    $monitor($time, ": rst=%b clk=%b load=%b data=%d cin=%b cout=%b qout=0x%X", 
        rst,clk,load,data,cin,cout,qout);

// 生成vcd波形文件
initial begin
    $dumpfile("./build/counter4_8_wave.vcd");
    $dumpvars(0, counter4_8_tb);  // 指定层次数为0，顶层模块为 xx
end

endmodule

code/learn/verilog_examples/03_counter/counter/build/counter4_8_wave.vcd
$date
	Wed Aug 04 16:35:28 2021
$end
$version
	Icarus Verilog
$end
$timescale
	1ns
$end
$scope module counter4_8_tb $end
$var wire 8 ! qout [7:0] $end
$var wire 1 " cout $end
$var reg 1 # cin $end
$var reg 1 $ clk $end
$var reg 8 % data [7:0] $end
$var reg 1 & load $end
$var reg 1 ' rst $end
$scope module uc $end
$var wire 1 # cin $end
$var wire 1 $ clk $end
$var wire 8 ( data [7:0] $end
$var wire 1 & load $end
$var wire 1 ' rst $end
$var wire 1 " cout $end
$var reg 8 ) qout [7:0] $end
$upscope $end
$upscope $end
$enddefinitions $end
#0
$dumpvars
bx )
b100100 (
0'
0&
b100100 %
0$
0#
0"
bx !
$end
#10
1$
#20
0$
1'
#30
b0 !
b0 )
1$
#40
0$
0'
#50
1$
#60
0$
#70
1$
#80
0$
#90
1$
#100
0$
1#
#110
b1 !
b1 )
1$
#120
0$
#130
b10 !
b10 )
1$
#140
0$
#150
b11 !
b11 )
1$
#160
0$
#170
b100 !
b100 )
1$
#180
0$
#190
b101 !
b101 )
1$
#200
0$
0#
#210
1$
#220
0$
#230
1$
#240
0$
#250
1$
#260
0$
1&
#270
b100100 !
b100100 )
1$
#280
0$
0&
#290
1$
#300
0$
1#
#310
b100101 !
b100101 )
1$
#320
0$
#330
b100110 !
b100110 )
1$
#340
0$
#350
b100111 !
b100111 )
1$
#360
0$
#370
b101000 !
b101000 )
1$
#380
0$
#390
b101001 !
b101001 )
1$
#400
0$
0#
#410
1$
#420
0$
#430
1$
#440
0$
#450
1$
#460
0$
#470
1$
#480
0$
#490
1$
#500
0$
1#
#510
b110000 !
b110000 )
1$
#520
0$
#530
b110001 !
b110001 )
1$
#540
0$
#550
b110010 !
b110010 )
1$
#560
0$
#570
b110011 !
b110011 )
1$
#580
0$
#590
b110100 !
b110100 )
1$
#600
0$
0#
#610
1$
#620
0$
#630
1$
#640
0$
#650
1$
#660
0$
#670
1$
#680
0$
#690
1$
#700
0$
1#
#710
b110101 !
b110101 )
1$
#720
0$
#730
b110110 !
b110110 )
1$
#740
0$
#750
b110111 !
b110111 )
1$
#760
0$
#770
b111000 !
b111000 )
1$
#780
0$
#790
b111001 !
b111001 )
1$
#800
0$
0#
#810
1$
#820
0$
#830
1$
#840
0$
#850
1$
#860
0$
#870
1$
#880
0$
#890
1$
#900
0$
1#
#910
b1000000 !
b1000000 )
1$
#920
0$
#930
b1000001 !
b1000001 )
1$
#940
0$
#950
b1000010 !
b1000010 )
1$
#960
0$
#970
b1000011 !
b1000011 )
1$
#980
0$
#990
b1000100 !
b1000100 )
1$
#1000
0$
0#
#1010
1$
#1020
0$
#1030
1$
#1040
0$
#1050
1$
#1060
0$
#1070
1$
#1080
0$
#1090
1$
#1100
0$
1#
#1110
b1000101 !
b1000101 )
1$
#1120
0$
#1130
b1000110 !
b1000110 )
1$
#1140
0$
#1150
b1000111 !
b1000111 )
1$
#1160
0$
#1170
b1001000 !
b1001000 )
1$
#1180
0$
#1190
b1001001 !
b1001001 )
1$
#1200
0$
0#
#1210
1$
#1220
0$
#1230
1$
#1240
0$
#1250
1$
#1260
0$
#1270
1$
#1280
0$
#1290
1$
#1300
0$
1#
#1310
b1010000 !
b1010000 )
1$
#1320
0$
#1330
b1010001 !
b1010001 )
1$
#1340
0$
#1350
b1010010 !
b1010010 )
1$
#1360
0$
#1370
b1010011 !
b1010011 )
1$
#1380
0$
#1390
b1010100 !
b1010100 )
1$
#1400
0$
0#
#1410
1$
#1420
0$
#1430
1$
#1440
0$
#1450
1$
#1460
0$
#1470
1$
#1480
0$
#1490
1$
#1500
0$
1#
#1510
b1010101 !
b1010101 )
1$
#1520
0$
#1530
b1010110 !
b1010110 )
1$
#1540
0$
#1550
b1010111 !
b1010111 )
1$
#1560
0$
#1570
b1011000 !
b1011000 )
1$
#1580
0$
#1590
1"
b1011001 !
b1011001 )
1$
#1600
0"
0$
0#
#1610
1$
#1620
0$
#1630
1$
#1640
0$
#1650
1$
#1660
0$
#1670
1$
#1680
0$
#1690
1$
#1700
1"
0$
1#
#1710
0"
b0 !
b0 )
1$
#1720
0$
#1730
b1 !
b1 )
1$
#1740
0$
#1750
b10 !
b10 )
1$
#1760
0$
#1770
b11 !
b11 )
1$
#1780
0$
#1790
b100 !
b100 )
1$
#1800
0$
0#
#1810
1$
#1820
0$
#1830
1$
#1840
0$
#1850
1$
#1860
0$
#1870
1$
#1880
0$
#1890
1$
#1900
0$
1#
#1910
b101 !
b101 )
1$
#1920
0$
#1930
b110 !
b110 )
1$
#1940
0$
#1950
b111 !
b111 )
1$
#1960
0$
#1970
b1000 !
b1000 )
1$
#1980
0$
#1990
b1001 !
b1001 )
1$
#2000
0$
0#
#2010
1$
#2020
0$
#2030
1$
#2040
0$
#2050
1$
#2060
0$
#2070
1$
#2080
0$
#2090
1$
#2100
0$
1#
#2110
b10000 !
b10000 )
1$
#2120
0$
#2130
b10001 !
b10001 )
1$
#2140
0$
#2150
b10010 !
b10010 )
1$
#2160
0$
#2170
b10011 !
b10011 )
1$
#2180
0$
#2190
b10100 !
b10100 )
1$
#2200
0$
0#
#2210
1$
#2220
0$
#2230
1$
#2240
0$
#2250
1$
#2260
0$
#2270
1$
#2280
0$
#2290
1$
#2300
0$
1#
#2310
b10101 !
b10101 )
1$
#2320
0$
#2330
b10110 !
b10110 )
1$
#2340
0$
#2350
b10111 !
b10111 )
1$
#2360
0$
#2370
b11000 !
b11000 )
1$
#2380
0$
#2390
b11001 !
b11001 )
1$
#2400
0$
0#
#2410
1$
#2420
0$
#2430
1$
#2440
0$
#2450
1$
#2460
0$
#2470
1$
#2480
0$
#2490
1$
#2500
0$
1#
#2510
b100000 !
b100000 )
1$
#2520
0$
#2530
b100001 !
b100001 )
1$
#2540
0$
#2550
b100010 !
b100010 )
1$
#2560
0$
#2570
b100011 !
b100011 )
1$
#2580
0$
#2590
b100100 !
b100100 )
1$
#2600
0$
0#
#2610
1$
#2620
0$
#2630
1$
#2640
0$
#2650
1$
#2660
0$
#2670
1$
#2680
0$
#2690
1$
#2700
0$
1#
#2710
b100101 !
b100101 )
1$
#2720
0$
#2730
b100110 !
b100110 )
1$
#2740
0$
#2750
b100111 !
b100111 )
1$
#2760
0$
#2770
b101000 !
b101000 )
1$
#2780
0$
#2790
b101001 !
b101001 )
1$
#2800
0$
0#
#2810
1$
#2820
0$
#2830
1$
#2840
0$
#2850
1$
#2860
0$
#2870
1$
#2880
0$
#2890
1$
#2900
0$
1#
#2910
b110000 !
b110000 )
1$
#2920
0$
#2930
b110001 !
b110001 )
1$
#2940
0$
#2950
b110010 !
b110010 )
1$
#2960
0$
#2970
b110011 !
b110011 )
1$
#2980
0$
#2990
b110100 !
b110100 )
1$
#3000
0$
0#
#3010
1$
#3020
0$
#3030
1$
#3040
0$
#3050
1$
#3060
0$
#3070
1$
#3080
0$
#3090
1$
#3100
0$
1#
#3110
b110101 !
b110101 )
1$
#3120
0$
#3130
b110110 !
b110110 )
1$
#3140
0$
#3150
b110111 !
b110111 )
1$
#3160
0$
#3170
b111000 !
b111000 )
1$
#3180
0$
#3190
b111001 !
b111001 )
1$
#3200
0$
0#
#3210
1$
#3220
0$
#3230
1$
#3240
0$
#3250
1$
#3260
0$
#3270
1$
#3280
0$
#3290
1$
#3300
0$
1#
#3310
b1000000 !
b1000000 )
1$
#3320
0$
#3330
b1000001 !
b1000001 )
1$
#3340
0$
#3350
b1000010 !
b1000010 )
1$
#3360
0$
#3370
b1000011 !
b1000011 )
1$
#3380
0$
#3390
b1000100 !
b1000100 )
1$
#3400
0$
0#
#3410
1$
#3420
0$
#3430
1$
#3440
0$
#3450
1$
#3460
0$
#3470
1$
#3480
0$
#3490
1$
#3500
0$
1#
#3510
b1000101 !
b1000101 )
1$
#3520
0$
#3530
b1000110 !
b1000110 )
1$
#3540
0$
#3550
b1000111 !
b1000111 )
1$
#3560
0$
#3570
b1001000 !
b1001000 )
1$
#3580
0$
#3590
b1001001 !
b1001001 )
1$
#3600
0$
0#
#3610
1$
#3620
0$
#3630
1$
#3640
0$
#3650
1$
#3660
0$
#3670
1$
#3680
0$
#3690
1$
#3700
0$
1#
#3710
b1010000 !
b1010000 )
1$
#3720
0$
#3730
b1010001 !
b1010001 )
1$
#3740
0$
#3750
b1010010 !
b1010010 )
1$
#3760
0$
#3770
b1010011 !
b1010011 )
1$
#3780
0$
#3790
b1010100 !
b1010100 )
1$
#3800
0$
0#
#3810
1$
#3820
0$
#3830
1$
#3840
0$
#3850
1$
#3860
0$
#3870
1$
#3880
0$
#3890
1$
#3900
0$
1#
#3910
b1010101 !
b1010101 )
1$
#3920
0$
#3930
b1010110 !
b1010110 )
1$
#3940
0$
#3950
b1010111 !
b1010111 )
1$
#3960
0$
#3970
b1011000 !
b1011000 )
1$
#3980
0$
#3990
1"
b1011001 !
b1011001 )
1$
#4000
0"
0$
0#
#4010
1$
#4020
0$
#4030
1$
#4040
0$
#4050
1$
#4060
0$
#4070
1$
#4080
0$
#4090
1$
#4100
1"
0$
1#
#4110
0"
b0 !
b0 )
1$
#4120
0$
#4130
b1 !
b1 )
1$
#4140
0$
#4150
b10 !
b10 )
1$
#4160
0$
#4170
b11 !
b11 )
1$
#4180
0$
#4190
b100 !
b100 )
1$
#4200
0$
0#
