code/learn/verilog_examples/03_counter/counter/counter4_1.v
// 4位计数器

// 同步复位，边沿触发，行为描述的
module counter4_1(out,clk,rst);
output [3:0] out;
input clk,rst;
reg [3:0] out;

always @(posedge clk) begin
    if (rst) out <= 0;
    else out <= out + 1;
end

endmodule

code/learn/verilog_examples/03_counter/counter/counter4_1_tb.v
// 4位计数器的仿真程序
`timescale 1ns/1ns
`include "counter4_1.v"
module counter4_1_tb;
reg clk,rst;
wire [3:0] out;
parameter DELAY = 20;

counter4_1 uc4(out,clk,rst);


always #(DELAY/2) clk = ~clk;

initial begin
            clk = 0; rst = 0;
    #DELAY  rst = 1;
    #DELAY  rst = 0;
    #(DELAY*20)
            $finish;
end

// 打印信号
initial 
    $monitor($time, ":rst=%b clk=%b out=%d", rst,clk,out);

// 生成vcd波形文件
initial begin
    $dumpfile("./build/counter4_1_wave.vcd");
    $dumpvars(0, counter4_1_tb);  // 指定层次数为0，顶层模块为 counter4_tb
    #10000 $finish;
end

endmodule

code/learn/verilog_examples/03_counter/counter/build/counter4_1_wave.vcd
$date
	Wed Aug 04 08:36:12 2021
$end
$version
	Icarus Verilog
$end
$timescale
	1ns
$end
$scope module counter4_1_tb $end
$var wire 4 ! out [3:0] $end
$var reg 1 " clk $end
$var reg 1 # rst $end
$scope module uc4 $end
$var wire 1 " clk $end
$var wire 1 # rst $end
$var reg 4 $ out [3:0] $end
$upscope $end
$upscope $end
$enddefinitions $end
#0
$dumpvars
bx $
0#
0"
bx !
$end
#10
1"
#20
0"
1#
#30
b0 !
b0 $
1"
#40
0"
0#
#50
b1 !
b1 $
1"
#60
0"
#70
b10 !
b10 $
1"
#80
0"
#90
b11 !
b11 $
1"
#100
0"
#110
b100 !
b100 $
1"
#120
0"
#130
b101 !
b101 $
1"
#140
0"
#150
b110 !
b110 $
1"
#160
0"
#170
b111 !
b111 $
1"
#180
0"
#190
b1000 !
b1000 $
1"
#200
0"
#210
b1001 !
b1001 $
1"
#220
0"
#230
b1010 !
b1010 $
1"
#240
0"
#250
b1011 !
b1011 $
1"
#260
0"
#270
b1100 !
b1100 $
1"
#280
0"
#290
b1101 !
b1101 $
1"
#300
0"
#310
b1110 !
b1110 $
1"
#320
0"
#330
b1111 !
b1111 $
1"
#340
0"
#350
b0 !
b0 $
1"
#360
0"
#370
b1 !
b1 $
1"
#380
0"
#390
b10 !
b10 $
1"
#400
0"
#410
b11 !
b11 $
1"
#420
0"
#430
b100 !
b100 $
1"
