code/learn/verilog_examples/05_multiplier/mult/MAC.v
// 乘累加器（MAC : Multiply-ACcumulator)
module MAC(out,a,b,clk,clr);
    output [15:0] out;
    input [7:0] a,b;
    input clk,clr;
    wire [15:0] sum;
    reg [15:0] out;

    // mult函数完成乘法操作
    function [15:0] mult;
        input [7:0] a,b;
        reg [15:0] result;
        integer i;

        begin
            result = a[0] ? b : 0;
            for (i = 1; i <= 7; i = i + 1) begin
                if (a[i]) result = result + (b << (i - 1));
            end
            mult = result;
        end
    endfunction

    // 乘累加
    assign sum = mult(a,b) + out;

    // 送出数据
    always @(posedge clk or posedge clr) begin
        if (clr) out <= 0;
        else out <= sum;
    end
endmodule

code/learn/verilog_examples/05_multiplier/mult/MAC_tb.v
`timescale 1ns/1ns
`include "MAC.v"
module MAC_tb;
    reg [7:0] a,b;
    reg clr,clk;
    wire [15:0] out;
    parameter DELAY = 20;

    MAC u1(out,a,b,clk,clr);

    always #(DELAY) clk = ~clk;

    // 激励信号定义
    initial begin
        clr = 1; clk = 0; a = 8'd0; b = 8'd0;
        #DELAY clr = 0; a = 8'd1; b = 8'd10;
        #DELAY a = 8'd2;
        #DELAY a = 8'd3;
        #DELAY a = 8'd4;
        #DELAY a = 8'd5;
        #DELAY a = 8'd6;
        #DELAY a = 8'd7;
        #DELAY a = 8'd8;
        #DELAY a = 8'd9;
        #DELAY a = 8'd10;
        #DELAY $finish;
    end

    // 打印信号
    initial 
        $monitor($time, ": clr=%b clk=%b a=%d b=%d out=%d", clr,clk,a,b,out);

    // 生成vcd波形文件
    initial begin
        $dumpfile("./build/MAC_tb_wave.vcd");
        $dumpvars(0, MAC_tb);
    end
endmodule //MAC_tb

code/learn/verilog_examples/05_multiplier/mult/build/MAC_tb_wave.vcd
$date
	Wed Aug 04 22:28:01 2021
$end
$version
	Icarus Verilog
$end
$timescale
	1ns
$end
$scope module MAC_tb $end
$var wire 16 ! out [15:0] $end
$var reg 8 " a [7:0] $end
$var reg 8 # b [7:0] $end
$var reg 1 $ clk $end
$var reg 1 % clr $end
$scope module u1 $end
$var wire 8 & a [7:0] $end
$var wire 8 ' b [7:0] $end
$var wire 1 $ clk $end
$var wire 1 % clr $end
$var wire 16 ( sum [15:0] $end
$var reg 16 ) out [15:0] $end
$scope function mult $end
$var reg 8 * a [7:0] $end
$var reg 8 + b [7:0] $end
$var reg 16 , result [15:0] $end
$var integer 32 - i [31:0] $end
$upscope $end
$upscope $end
$upscope $end
$enddefinitions $end
#0
$dumpvars
b1000 -
b0 ,
b0 +
b0 *
b0 )
b0 (
b0 '
b0 &
1%
0$
b0 #
b0 "
b0 !
$end
#20
b1010 (
b1000 -
b1010 ,
b1010 +
b1 *
b1010 #
b1010 '
b1 "
b1 &
0%
1$
#40
b1000 -
b1010 ,
b10 *
b10 "
b10 &
0$
#60
b1010 !
b1010 )
b11110 (
b10100 ,
b1000 -
b11 *
b11 "
b11 &
1$
#80
b1000 -
b10100 ,
b100 *
b100 "
b100 &
0$
#100
b11110 !
b11110 )
b111100 (
b1000 -
b11110 ,
b101 *
b101 "
b101 &
1$
#120
b1000 -
b11110 ,
b110 *
b110 "
b110 &
0$
#140
b111100 !
b111100 )
b1100100 (
b1000 -
b101000 ,
b111 *
b111 "
b111 &
1$
#160
b1000 -
b101000 ,
b1000 *
b1000 "
b1000 &
0$
#180
b1100100 !
b1100100 )
b10010110 (
b1000 -
b110010 ,
b1001 *
b1001 "
b1001 &
1$
#200
b1000 -
b110010 ,
b1010 *
b1010 "
b1010 &
0$
#220
b11001000 (
b10010110 !
b10010110 )
1$
