code/learn/iverilator_examples/ex3/src/mut2.v
// 二选一数据选择器
// sel = 0 时，out = a
// sel = 1 时，out = b
module mut2 (out,
            a,
            b,
            sel);
    input a,b,sel;
    output out;
    wire selnot,a1,b1;

    not U1(selnot,sel);     // selnot = !sel
    and U2(a1,a,selnot);    // a1 = a && selnot
    and U3(b1, b, sel);     // b1 = b && sel
    or  U4(out, a1, b1);    // out = a1 || b1

endmodule //mut2

code/learn/iverilator_examples/ex3/src/tb_mut2.v
`timescale 1ns/1ns      // 时间单位1ns，时间精度1ns
module tb_mut2;
    reg a,b,s;  // 激励变量为reg，以保证激励持续保持不变
    wire out;

    // 实例化
    mut2 u1(.out(out), .a(a), .b(b), .sel(s));

    // 行为描述语句
    // 描述输入信号
    initial begin
        a = 0; b = 0; s = 0;
    #10 a = 0; b = 1; s = 0;
    #10 a = 1; b = 0; s = 0;
    #10 a = 1; b = 1; s = 0;
    #10 a = 0; b = 0; s = 1;
    #10 a = 0; b = 1; s = 1;
    #10 a = 1; b = 0; s = 1;
    #10 a = 1; b = 1; s = 1;
    end

    // 描述输出信号
    initial 
        $monitor($time, ":a=%b b=%b s=%b out=%b", a, b, s, out);
    
    // 生成vcd波形文件
    initial begin
        $dumpfile("./build/wave.vcd");
        $dumpvars(0, tb_mut2);  // 指定层次数为0，顶层模块为tb_code
        #10000 $finish;
    end

endmodule //tb_mut2

code/learn/iverilator_examples/ex3/build/wave.vcd
$date
	Wed Jul 28 17:28:04 2021
$end
$version
	Icarus Verilog
$end
$timescale
	1ns
$end
$scope module tb_mut2 $end
$var wire 1 ! out $end
$var reg 1 " a $end
$var reg 1 # b $end
$var reg 1 $ s $end
$scope module u1 $end
$var wire 1 " a $end
$var wire 1 % a1 $end
$var wire 1 # b $end
$var wire 1 & b1 $end
$var wire 1 ! out $end
$var wire 1 $ sel $end
$var wire 1 ' selnot $end
$upscope $end
$upscope $end
$enddefinitions $end
#0
$dumpvars
1'
0&
0%
0$
0#
0"
0!
$end
#10
1#
#20
1!
1%
0#
1"
#30
1#
#40
0!
0'
0%
1$
0#
0"
#50
1!
1&
1#
#60
0!
0&
0#
1"
#70
1!
1&
1#
